[{"event_type": "order", "order_hash": "0xd7531a24eadc2a706f3b2e5db54732d1384ca7893773947420c0dbfa54e48e2b", "order_type": "collection_offer", "chain": "base", "protocol_address": "0x0000000000000068f116a894984e2db1123eb395", "start_date": 1729699787, "expiration_date": 1729701287, "asset": null, "quantity": 20, "maker": "0xd4f4f6a1f386e041984da38e7be351903c767c2d", "taker": "", "payment": {"quantity": "4000000000000000", "token_address": "0x4200000000000000000000000000000000000006", "decimals": 18, "symbol": "WETH"}, "criteria": {"collection": {"slug": "boredape-baseclub"}, "contract": {"address": "0x0be0bb1097f4465b17b1ac3b22b5427d9cbf6d2c"}, "trait": null, "encoded_token_ids": null}, "event_timestamp": 1729699789, "is_private_listing": false}, {"event_type": "order", "order_hash": "0xd5c6d4b2a26b6ddb44fd52218275d48ee7dcba8420bdd750048004ca1c9d2caf", "order_type": "collection_offer", "chain": "base", "protocol_address": "0x0000000000000068f116a894984e2db1123eb395", "start_date": 1729699030, "expiration_date": 1729700529, "asset": null, "quantity": 4, "maker": "0xd4f4f6a1f386e041984da38e7be351903c767c2d", "taker": "", "payment": {"quantity": "4400000000000000", "token_address": "0x4200000000000000000000000000000000000006", "decimals": 18, "symbol": "WETH"}, "criteria": {"collection": {"slug": "boredape-baseclub"}, "contract": {"address": "0x0be0bb1097f4465b17b1ac3b22b5427d9cbf6d2c"}, "trait": null, "encoded_token_ids": null}, "event_timestamp": 1729699032, "is_private_listing": false}, {"event_type": "order", "order_hash": "0xe8de592bb6ddc4c5a770e94e8c0a3deb054c106c86b3f5a6b8c453bea53dfec5", "order_type": "collection_offer", "chain": "base", "protocol_address": "0x0000000000000068f116a894984e2db1123eb395", "start_date": 1729699026, "expiration_date": 1729700525, "asset": null, "quantity": 4, "maker": "0xd4f4f6a1f386e041984da38e7be351903c767c2d", "taker": "", "payment": {"quantity": "3600000000000000", "token_address": "0x4200000000000000000000000000000000000006", "decimals": 18, "symbol": "WETH"}, "criteria": {"collection": {"slug": "boredape-baseclub"}, "contract": {"address": "0x0be0bb1097f4465b17b1ac3b22b5427d9cbf6d2c"}, "trait": null, "encoded_token_ids": null}, "event_timestamp": 1729699028, "is_private_listing": false}, {"event_type": "order", "order_hash": "0xa94db663cec489f259b820dc88d9dea382912fe0bf6a19d6339aed400f8fa0ff", "order_type": "collection_offer", "chain": "base", "protocol_address": "0x0000000000000068f116a894984e2db1123eb395", "start_date": 1729699022, "expiration_date": 1729700521, "asset": null, "quantity": 20, "maker": "0xd4f4f6a1f386e041984da38e7be351903c767c2d", "taker": "", "payment": {"quantity": "4000000000000000", "token_address": "0x4200000000000000000000000000000000000006", "decimals": 18, "symbol": "WETH"}, "criteria": {"collection": {"slug": "boredape-baseclub"}, "contract": {"address": "0x0be0bb1097f4465b17b1ac3b22b5427d9cbf6d2c"}, "trait": null, "encoded_token_ids": null}, "event_timestamp": 1729699024, "is_private_listing": false}, {"event_type": "order", "order_hash": "0xdd61af98de122d4961dfb11ceccf9206d3177262adfefa884df0632701614fb4", "order_type": "collection_offer", "chain": "base", "protocol_address": "0x0000000000000068f116a894984e2db1123eb395", "start_date": 1729698207, "expiration_date": 1729699707, "asset": null, "quantity": 4, "maker": "0xd4f4f6a1f386e041984da38e7be351903c767c2d", "taker": "", "payment": {"quantity": "4400000000000000", "token_address": "0x4200000000000000000000000000000000000006", "decimals": 18, "symbol": "WETH"}, "criteria": {"collection": {"slug": "boredape-baseclub"}, "contract": {"address": "0x0be0bb1097f4465b17b1ac3b22b5427d9cbf6d2c"}, "trait": null, "encoded_token_ids": null}, "event_timestamp": 1729698209, "is_private_listing": false}, {"event_type": "order", "order_hash": "0x07db57c3ecd08b322e46caf6f7e520955d8e0ae5340fd9782ac8319a26f38c25", "order_type": "collection_offer", "chain": "base", "protocol_address": "0x0000000000000068f116a894984e2db1123eb395", "start_date": 1729698204, "expiration_date": 1729699704, "asset": null, "quantity": 4, "maker": "0xd4f4f6a1f386e041984da38e7be351903c767c2d", "taker": "", "payment": {"quantity": "3600000000000000", "token_address": "0x4200000000000000000000000000000000000006", "decimals": 18, "symbol": "WETH"}, "criteria": {"collection": {"slug": "boredape-baseclub"}, "contract": {"address": "0x0be0bb1097f4465b17b1ac3b22b5427d9cbf6d2c"}, "trait": null, "encoded_token_ids": null}, "event_timestamp": 1729698206, "is_private_listing": false}, {"event_type": "order", "order_hash": "0x532254639c6af4f586ed555a394b126cc507c536378af3d1938e14356f5a2045", "order_type": "collection_offer", "chain": "base", "protocol_address": "0x0000000000000068f116a894984e2db1123eb395", "start_date": 1729698201, "expiration_date": 1729699700, "asset": null, "quantity": 20, "maker": "0xd4f4f6a1f386e041984da38e7be351903c767c2d", "taker": "", "payment": {"quantity": "4000000000000000", "token_address": "0x4200000000000000000000000000000000000006", "decimals": 18, "symbol": "WETH"}, "criteria": {"collection": {"slug": "boredape-baseclub"}, "contract": {"address": "0x0be0bb1097f4465b17b1ac3b22b5427d9cbf6d2c"}, "trait": null, "encoded_token_ids": null}, "event_timestamp": 1729698203, "is_private_listing": false}, {"event_type": "order", "order_hash": "0x18e8cefbf75fdcb9233e2922ea2fad700761037e6538833144f36dd6ac7ac8c7", "order_type": "listing", "chain": "base", "protocol_address": "0x0000000000000068f116a894984e2db1123eb395", "start_date": 1729697945, "expiration_date": 1732338108, "asset": {"identifier": "1694", "collection": "boredape-baseclub", "contract": "0x0be0bb1097f4465b17b1ac3b22b5427d9cbf6d2c", "token_standard": "erc721", "name": "BABC #1694", "description": "Discover the world of the Bored Ape Base Club (BABC) at boredapebaseclub.com , your exclusive gateway to a vibrant community on the Base Chain. Offering more than mere ownership, BABC NFTs act as a passport to an elite club for members only. By acquiring a BABC NFT, you gain access to private events and a chance to secure special edition Bitcoin NFTs. Join our community and explore the exclusive benefits awaiting BABC NFT holders.", "image_url": "https://ipfs.io/ipfs/bafybeickjcj3rry27fck5dm4unu3artwb7umu5fwq6l6rn5kydpcxzwela/1694", "display_image_url": "https://i.seadn.io/s/raw/files/6c2152d22c6aa173a482eed4e85fbf4e.png?w=500&auto=format", "display_animation_url": null, "metadata_url": "https://ipfs.io/ipfs/bafybeiacrqba67k6p7vu523mnumu36a34hcanowg4axxl2z3yse6ot437y/1694", "opensea_url": "https://opensea.io/assets/base/0x0be0bb1097f4465b17b1ac3b22b5427d9cbf6d2c/1694", "updated_at": "2024-11-15T09:22:41.729885", "is_disabled": false, "is_nsfw": false}, "quantity": 1, "maker": "0x51d12e39a053daa92fa14a7199dfe3d04a973fa0", "taker": "", "payment": {"quantity": "2990000000000000", "token_address": "0x0000000000000000000000000000000000000000", "decimals": 18, "symbol": "ETH"}, "criteria": {}, "event_timestamp": 1729697949, "is_private_listing": false}, {"event_type": "order", "order_hash": "0xc001d912dcc0b0e169455321e9c9891f206861f80f48102fc749d4f42188768e", "order_type": "collection_offer", "chain": "base", "protocol_address": "0x0000000000000068f116a894984e2db1123eb395", "start_date": 1729697265, "expiration_date": 1729698765, "asset": null, "quantity": 4, "maker": "0xd4f4f6a1f386e041984da38e7be351903c767c2d", "taker": "", "payment": {"quantity": "4400000000000000", "token_address": "0x4200000000000000000000000000000000000006", "decimals": 18, "symbol": "WETH"}, "criteria": {"collection": {"slug": "boredape-baseclub"}, "contract": {"address": "0x0be0bb1097f4465b17b1ac3b22b5427d9cbf6d2c"}, "trait": null, "encoded_token_ids": null}, "event_timestamp": 1729697267, "is_private_listing": false}, {"event_type": "order", "order_hash": "0x1402d3185fc54751d396cdbafce832e22a65c82a3226e3db3b35ccd6d8c57109", "order_type": "collection_offer", "chain": "base", "protocol_address": "0x0000000000000068f116a894984e2db1123eb395", "start_date": 1729697262, "expiration_date": 1729698762, "asset": null, "quantity": 4, "maker": "0xd4f4f6a1f386e041984da38e7be351903c767c2d", "taker": "", "payment": {"quantity": "3600000000000000", "token_address": "0x4200000000000000000000000000000000000006", "decimals": 18, "symbol": "WETH"}, "criteria": {"collection": {"slug": "boredape-baseclub"}, "contract": {"address": "0x0be0bb1097f4465b17b1ac3b22b5427d9cbf6d2c"}, "trait": null, "encoded_token_ids": null}, "event_timestamp": 1729697264, "is_private_listing": false}, {"event_type": "order", "order_hash": "0xe587bd6581de12b574e294d1dfefc29033627b4024f0bdf95f91496b7e0b231f", "order_type": "collection_offer", "chain": "base", "protocol_address": "0x0000000000000068f116a894984e2db1123eb395", "start_date": 1729697259, "expiration_date": 1729698759, "asset": null, "quantity": 20, "maker": "0xd4f4f6a1f386e041984da38e7be351903c767c2d", "taker": "", "payment": {"quantity": "4000000000000000", "token_address": "0x4200000000000000000000000000000000000006", "decimals": 18, "symbol": "WETH"}, "criteria": {"collection": {"slug": "boredape-baseclub"}, "contract": {"address": "0x0be0bb1097f4465b17b1ac3b22b5427d9cbf6d2c"}, "trait": null, "encoded_token_ids": null}, "event_timestamp": 1729697261, "is_private_listing": false}, {"event_type": "order", "order_hash": "0x8a2ae41520978835b2d9677d12cb5add7a64a14c3459c9560ffd3888c7ea226c", "order_type": "collection_offer", "chain": "base", "protocol_address": "0x0000000000000068f116a894984e2db1123eb395", "start_date": 1729696542, "expiration_date": 1729698042, "asset": null, "quantity": 4, "maker": "0xd4f4f6a1f386e041984da38e7be351903c767c2d", "taker": "", "payment": {"quantity": "4400000000000000", "token_address": "0x4200000000000000000000000000000000000006", "decimals": 18, "symbol": "WETH"}, "criteria": {"collection": {"slug": "boredape-baseclub"}, "contract": {"address": "0x0be0bb1097f4465b17b1ac3b22b5427d9cbf6d2c"}, "trait": null, "encoded_token_ids": null}, "event_timestamp": 1729696544, "is_private_listing": false}, {"event_type": "order", "order_hash": "0x66bf49067ec6913e0081a566af60264a971de29be35bc0589d230cefd87eb240", "order_type": "collection_offer", "chain": "base", "protocol_address": "0x0000000000000068f116a894984e2db1123eb395", "start_date": 1729696538, "expiration_date": 1729698038, "asset": null, "quantity": 4, "maker": "0xd4f4f6a1f386e041984da38e7be351903c767c2d", "taker": "", "payment": {"quantity": "3600000000000000", "token_address": "0x4200000000000000000000000000000000000006", "decimals": 18, "symbol": "WETH"}, "criteria": {"collection": {"slug": "boredape-baseclub"}, "contract": {"address": "0x0be0bb1097f4465b17b1ac3b22b5427d9cbf6d2c"}, "trait": null, "encoded_token_ids": null}, "event_timestamp": 1729696540, "is_private_listing": false}, {"event_type": "order", "order_hash": "0x5dae8b2ceafe3b87743521ac22c9b02a497bd38af3c9810b6ff81315ee9cd41b", "order_type": "collection_offer", "chain": "base", "protocol_address": "0x0000000000000068f116a894984e2db1123eb395", "start_date": 1729696535, "expiration_date": 1729698035, "asset": null, "quantity": 20, "maker": "0xd4f4f6a1f386e041984da38e7be351903c767c2d", "taker": "", "payment": {"quantity": "4000000000000000", "token_address": "0x4200000000000000000000000000000000000006", "decimals": 18, "symbol": "WETH"}, "criteria": {"collection": {"slug": "boredape-baseclub"}, "contract": {"address": "0x0be0bb1097f4465b17b1ac3b22b5427d9cbf6d2c"}, "trait": null, "encoded_token_ids": null}, "event_timestamp": 1729696537, "is_private_listing": false}, {"event_type": "order", "order_hash": "0x49588440f96856796d1c784de5bf8c38fea3bffd81b6197aae3f36f2c80c4aa2", "order_type": "collection_offer", "chain": "base", "protocol_address": "0x0000000000000068f116a894984e2db1123eb395", "start_date": 1729695825, "expiration_date": 1729697324, "asset": null, "quantity": 4, "maker": "0xd4f4f6a1f386e041984da38e7be351903c767c2d", "taker": "", "payment": {"quantity": "4400000000000000", "token_address": "0x4200000000000000000000000000000000000006", "decimals": 18, "symbol": "WETH"}, "criteria": {"collection": {"slug": "boredape-baseclub"}, "contract": {"address": "0x0be0bb1097f4465b17b1ac3b22b5427d9cbf6d2c"}, "trait": null, "encoded_token_ids": null}, "event_timestamp": 1729695827, "is_private_listing": false}, {"event_type": "order", "order_hash": "0x401fd54a55ca83ec7d3bd84e7da9122a2c3d6c3ce080de8725150fed156291dc", "order_type": "collection_offer", "chain": "base", "protocol_address": "0x0000000000000068f116a894984e2db1123eb395", "start_date": 1729695821, "expiration_date": 1729697321, "asset": null, "quantity": 4, "maker": "0xd4f4f6a1f386e041984da38e7be351903c767c2d", "taker": "", "payment": {"quantity": "3600000000000000", "token_address": "0x4200000000000000000000000000000000000006", "decimals": 18, "symbol": "WETH"}, "criteria": {"collection": {"slug": "boredape-baseclub"}, "contract": {"address": "0x0be0bb1097f4465b17b1ac3b22b5427d9cbf6d2c"}, "trait": null, "encoded_token_ids": null}, "event_timestamp": 1729695823, "is_private_listing": false}, {"event_type": "order", "order_hash": "0xe6679997dbaa2602440978aa0d468a18a0a0f3d9e1d59b5051208d24045d7c7f", "order_type": "collection_offer", "chain": "base", "protocol_address": "0x0000000000000068f116a894984e2db1123eb395", "start_date": 1729695818, "expiration_date": 1729697318, "asset": null, "quantity": 20, "maker": "0xd4f4f6a1f386e041984da38e7be351903c767c2d", "taker": "", "payment": {"quantity": "4000000000000000", "token_address": "0x4200000000000000000000000000000000000006", "decimals": 18, "symbol": "WETH"}, "criteria": {"collection": {"slug": "boredape-baseclub"}, "contract": {"address": "0x0be0bb1097f4465b17b1ac3b22b5427d9cbf6d2c"}, "trait": null, "encoded_token_ids": null}, "event_timestamp": 1729695820, "is_private_listing": false}, {"event_type": "order", "order_hash": "0xd6b071e9da9c149a234ccf1c34a41e41d944c066e8c50dd3e82d0b6323fd7b4b", "order_type": "collection_offer", "chain": "base", "protocol_address": "0x0000000000000068f116a894984e2db1123eb395", "start_date": 1729694826, "expiration_date": 1729696326, "asset": null, "quantity": 4, "maker": "0xd4f4f6a1f386e041984da38e7be351903c767c2d", "taker": "", "payment": {"quantity": "4400000000000000", "token_address": "0x4200000000000000000000000000000000000006", "decimals": 18, "symbol": "WETH"}, "criteria": {"collection": {"slug": "boredape-baseclub"}, "contract": {"address": "0x0be0bb1097f4465b17b1ac3b22b5427d9cbf6d2c"}, "trait": null, "encoded_token_ids": null}, "event_timestamp": 1729694828, "is_private_listing": false}, {"event_type": "order", "order_hash": "0xfb5b9f3158bf6a51e0df5aa3a7dc7b91b031c2e0de1084486bf880953a4a84d7", "order_type": "collection_offer", "chain": "base", "protocol_address": "0x0000000000000068f116a894984e2db1123eb395", "start_date": 1729694823, "expiration_date": 1729696323, "asset": null, "quantity": 4, "maker": "0xd4f4f6a1f386e041984da38e7be351903c767c2d", "taker": "", "payment": {"quantity": "3600000000000000", "token_address": "0x4200000000000000000000000000000000000006", "decimals": 18, "symbol": "WETH"}, "criteria": {"collection": {"slug": "boredape-baseclub"}, "contract": {"address": "0x0be0bb1097f4465b17b1ac3b22b5427d9cbf6d2c"}, "trait": null, "encoded_token_ids": null}, "event_timestamp": 1729694825, "is_private_listing": false}, {"event_type": "order", "order_hash": "0xe1b2f0c0912739dde730c4afc5cf7745b47e1f911209fb2bd087a85cbc86dab1", "order_type": "collection_offer", "chain": "base", "protocol_address": "0x0000000000000068f116a894984e2db1123eb395", "start_date": 1729694820, "expiration_date": 1729696320, "asset": null, "quantity": 20, "maker": "0xd4f4f6a1f386e041984da38e7be351903c767c2d", "taker": "", "payment": {"quantity": "4000000000000000", "token_address": "0x4200000000000000000000000000000000000006", "decimals": 18, "symbol": "WETH"}, "criteria": {"collection": {"slug": "boredape-baseclub"}, "contract": {"address": "0x0be0bb1097f4465b17b1ac3b22b5427d9cbf6d2c"}, "trait": null, "encoded_token_ids": null}, "event_timestamp": 1729694822, "is_private_listing": false}, {"event_type": "order", "order_hash": "0x8bb0635de411af13eadd43ccd63d4d556420d53638c6656891b6d51b5199070f", "order_type": "collection_offer", "chain": "base", "protocol_address": "0x0000000000000068f116a894984e2db1123eb395", "start_date": 1729694120, "expiration_date": 1729695620, "asset": null, "quantity": 4, "maker": "0xd4f4f6a1f386e041984da38e7be351903c767c2d", "taker": "", "payment": {"quantity": "4400000000000000", "token_address": "0x4200000000000000000000000000000000000006", "decimals": 18, "symbol": "WETH"}, "criteria": {"collection": {"slug": "boredape-baseclub"}, "contract": {"address": "0x0be0bb1097f4465b17b1ac3b22b5427d9cbf6d2c"}, "trait": null, "encoded_token_ids": null}, "event_timestamp": 1729694122, "is_private_listing": false}, {"event_type": "order", "order_hash": "0x3ebe2aec3f134e7362ac3ebdc58fc3fe1c8e77a89bc19c60900222814e3f60ba", "order_type": "collection_offer", "chain": "base", "protocol_address": "0x0000000000000068f116a894984e2db1123eb395", "start_date": 1729694117, "expiration_date": 1729695616, "asset": null, "quantity": 4, "maker": "0xd4f4f6a1f386e041984da38e7be351903c767c2d", "taker": "", "payment": {"quantity": "3600000000000000", "token_address": "0x4200000000000000000000000000000000000006", "decimals": 18, "symbol": "WETH"}, "criteria": {"collection": {"slug": "boredape-baseclub"}, "contract": {"address": "0x0be0bb1097f4465b17b1ac3b22b5427d9cbf6d2c"}, "trait": null, "encoded_token_ids": null}, "event_timestamp": 1729694119, "is_private_listing": false}, {"event_type": "order", "order_hash": "0x0ff9f61421f8edee06fbfeb662d118c26fe6a7cf8f7388bd9e05ebdae98e6bdc", "order_type": "collection_offer", "chain": "base", "protocol_address": "0x0000000000000068f116a894984e2db1123eb395", "start_date": 1729694113, "expiration_date": 1729695613, "asset": null, "quantity": 20, "maker": "0xd4f4f6a1f386e041984da38e7be351903c767c2d", "taker": "", "payment": {"quantity": "4000000000000000", "token_address": "0x4200000000000000000000000000000000000006", "decimals": 18, "symbol": "WETH"}, "criteria": {"collection": {"slug": "boredape-baseclub"}, "contract": {"address": "0x0be0bb1097f4465b17b1ac3b22b5427d9cbf6d2c"}, "trait": null, "encoded_token_ids": null}, "event_timestamp": 1729694115, "is_private_listing": false}, {"event_type": "order", "order_hash": "0x8c06d22b96d8ec6740bfdf9c5e34566125322c0bef8b8a335c4278d529342cda", "order_type": "collection_offer", "chain": "base", "protocol_address": "0x0000000000000068f116a894984e2db1123eb395", "start_date": 1729693424, "expiration_date": 1729694924, "asset": null, "quantity": 4, "maker": "0xd4f4f6a1f386e041984da38e7be351903c767c2d", "taker": "", "payment": {"quantity": "4400000000000000", "token_address": "0x4200000000000000000000000000000000000006", "decimals": 18, "symbol": "WETH"}, "criteria": {"collection": {"slug": "boredape-baseclub"}, "contract": {"address": "0x0be0bb1097f4465b17b1ac3b22b5427d9cbf6d2c"}, "trait": null, "encoded_token_ids": null}, "event_timestamp": 1729693426, "is_private_listing": false}, {"event_type": "order", "order_hash": "0xc5bad53403b267336d593947e8d9d6ec43edfa6b5711164988e3e835cba256fd", "order_type": "collection_offer", "chain": "base", "protocol_address": "0x0000000000000068f116a894984e2db1123eb395", "start_date": 1729693421, "expiration_date": 1729694921, "asset": null, "quantity": 4, "maker": "0xd4f4f6a1f386e041984da38e7be351903c767c2d", "taker": "", "payment": {"quantity": "3600000000000000", "token_address": "0x4200000000000000000000000000000000000006", "decimals": 18, "symbol": "WETH"}, "criteria": {"collection": {"slug": "boredape-baseclub"}, "contract": {"address": "0x0be0bb1097f4465b17b1ac3b22b5427d9cbf6d2c"}, "trait": null, "encoded_token_ids": null}, "event_timestamp": 1729693423, "is_private_listing": false}, {"event_type": "order", "order_hash": "0xc40784c148fffbed0b544de27f041bfe8da8bbdf46ac45dda8c0b388ad477293", "order_type": "listing", "chain": "base", "protocol_address": "0x0000000000000068f116a894984e2db1123eb395", "start_date": 1729693420, "expiration_date": 1729952619, "asset": {"identifier": "2023", "collection": "boredape-baseclub", "contract": "0x0be0bb1097f4465b17b1ac3b22b5427d9cbf6d2c", "token_standard": "erc721", "name": "BABC #2023", "description": "Discover the world of the Bored Ape Base Club (BABC) at boredapebaseclub.com , your exclusive gateway to a vibrant community on the Base Chain. Offering more than mere ownership, BABC NFTs act as a passport to an elite club for members only. By acquiring a BABC NFT, you gain access to private events and a chance to secure special edition Bitcoin NFTs. Join our community and explore the exclusive benefits awaiting BABC NFT holders.", "image_url": "https://ipfs.io/ipfs/bafybeie3ah6zeyvuqcj7z55ca6xfyl5anzcjsaobkyc637j56g4qioqtwa/2023", "display_image_url": "https://i.seadn.io/s/raw/files/654bd9c9e74804df72402c0893b53656.png?w=500&auto=format", "display_animation_url": null, "metadata_url": "https://ipfs.io/ipfs/bafybeiacrqba67k6p7vu523mnumu36a34hcanowg4axxl2z3yse6ot437y/2023", "opensea_url": "https://opensea.io/assets/base/0x0be0bb1097f4465b17b1ac3b22b5427d9cbf6d2c/2023", "updated_at": "2024-12-14T15:04:54.026839", "is_disabled": false, "is_nsfw": false}, "quantity": 1, "maker": "0xd4f4f6a1f386e041984da38e7be351903c767c2d", "taker": "", "payment": {"quantity": "6600000000000000", "token_address": "0x0000000000000000000000000000000000000000", "decimals": 18, "symbol": "ETH"}, "criteria": {}, "event_timestamp": 1729693422, "is_private_listing": false}, {"event_type": "order", "order_hash": "0x889333b4b3f6cddda207e3411760fc927638f1ea646512c32f65bad947f34df9", "order_type": "collection_offer", "chain": "base", "protocol_address": "0x0000000000000068f116a894984e2db1123eb395", "start_date": 1729693418, "expiration_date": 1729694918, "asset": null, "quantity": 20, "maker": "0xd4f4f6a1f386e041984da38e7be351903c767c2d", "taker": "", "payment": {"quantity": "4000000000000000", "token_address": "0x4200000000000000000000000000000000000006", "decimals": 18, "symbol": "WETH"}, "criteria": {"collection": {"slug": "boredape-baseclub"}, "contract": {"address": "0x0be0bb1097f4465b17b1ac3b22b5427d9cbf6d2c"}, "trait": null, "encoded_token_ids": null}, "event_timestamp": 1729693420, "is_private_listing": false}, {"event_type": "order", "order_hash": "0xa22c1c05ab36ed0c1b4ed47c49856ae5b0bef72855ef7d303eca00d4c6740a92", "order_type": "listing", "chain": "base", "protocol_address": "0x0000000000000068f116a894984e2db1123eb395", "start_date": 1729693412, "expiration_date": 1729952612, "asset": {"identifier": "2073", "collection": "boredape-baseclub", "contract": "0x0be0bb1097f4465b17b1ac3b22b5427d9cbf6d2c", "token_standard": "erc721", "name": "BABC #2073", "description": "Discover the world of the Bored Ape Base Club (BABC) at boredapebaseclub.com , your exclusive gateway to a vibrant community on the Base Chain. Offering more than mere ownership, BABC NFTs act as a passport to an elite club for members only. By acquiring a BABC NFT, you gain access to private events and a chance to secure special edition Bitcoin NFTs. Join our community and explore the exclusive benefits awaiting BABC NFT holders.", "image_url": "https://ipfs.io/ipfs/bafybeie3ah6zeyvuqcj7z55ca6xfyl5anzcjsaobkyc637j56g4qioqtwa/2073", "display_image_url": "https://i.seadn.io/s/raw/files/4595f908fa243aab8067c644a85ed671.png?w=500&auto=format", "display_animation_url": null, "metadata_url": "https://ipfs.io/ipfs/bafybeiacrqba67k6p7vu523mnumu36a34hcanowg4axxl2z3yse6ot437y/2073", "opensea_url": "https://opensea.io/assets/base/0x0be0bb1097f4465b17b1ac3b22b5427d9cbf6d2c/2073", "updated_at": "2024-12-06T19:39:57.602658", "is_disabled": false, "is_nsfw": false}, "quantity": 1, "maker": "0xd4f4f6a1f386e041984da38e7be351903c767c2d", "taker": "", "payment": {"quantity": "6600000000000000", "token_address": "0x0000000000000000000000000000000000000000", "decimals": 18, "symbol": "ETH"}, "criteria": {}, "event_timestamp": 1729693414, "is_private_listing": false}, {"event_type": "order", "order_hash": "0x36c04ff6a895c350b7d55bfaed3aeacd8c712a15b07790390bf82b11769822a3", "order_type": "listing", "chain": "base", "protocol_address": "0x0000000000000068f116a894984e2db1123eb395", "start_date": 1729692869, "expiration_date": 1731129073, "asset": {"identifier": "169", "collection": "boredape-baseclub", "contract": "0x0be0bb1097f4465b17b1ac3b22b5427d9cbf6d2c", "token_standard": "erc721", "name": "BABC #169", "description": "Discover the world of the Bored Ape Base Club (BABC) at boredapebaseclub.com , your exclusive gateway to a vibrant community on the Base Chain. Offering more than mere ownership, BABC NFTs act as a passport to an elite club for members only. By acquiring a BABC NFT, you gain access to private events and a chance to secure special edition Bitcoin NFTs. Join our community and explore the exclusive benefits awaiting BABC NFT holders.", "image_url": "https://ipfs.io/ipfs/bafybeihsvvgdlo5gxe4axsqw36rvc4toczkij2jqhkfriwdw2dgkpjpp2y/169", "display_image_url": "https://i.seadn.io/s/raw/files/0af7f826f0d445787604bc7e0d67d0ce.png?w=500&auto=format", "display_animation_url": null, "metadata_url": "https://ipfs.io/ipfs/bafybeiacrqba67k6p7vu523mnumu36a34hcanowg4axxl2z3yse6ot437y/169", "opensea_url": "https://opensea.io/assets/base/0x0be0bb1097f4465b17b1ac3b22b5427d9cbf6d2c/169", "updated_at": "2024-11-14T09:23:44.721533", "is_disabled": false, "is_nsfw": false}, "quantity": 1, "maker": "0x87999855c8b8a15d23e3bb9326b9ce6241fdde7b", "taker": "", "payment": {"quantity": "3000000000000000", "token_address": "0x0000000000000000000000000000000000000000", "decimals": 18, "symbol": "ETH"}, "criteria": {}, "event_timestamp": 1729692872, "is_private_listing": false}, {"event_type": "order", "order_hash": "0x49ca0541c60a2c56fc48b1b101c6de99e159d4daf63fd45d718fd1b65fcc46a1", "order_type": "collection_offer", "chain": "base", "protocol_address": "0x0000000000000068f116a894984e2db1123eb395", "start_date": 1729692711, "expiration_date": 1729694210, "asset": null, "quantity": 4, "maker": "0xd4f4f6a1f386e041984da38e7be351903c767c2d", "taker": "", "payment": {"quantity": "4800000000000000", "token_address": "0x4200000000000000000000000000000000000006", "decimals": 18, "symbol": "WETH"}, "criteria": {"collection": {"slug": "boredape-baseclub"}, "contract": {"address": "0x0be0bb1097f4465b17b1ac3b22b5427d9cbf6d2c"}, "trait": null, "encoded_token_ids": null}, "event_timestamp": 1729692713, "is_private_listing": false}, {"event_type": "order", "order_hash": "0xa5b18b4b76a9dff16ef05935737eaf7728eadedb3a669039ca23eef919b7022b", "order_type": "collection_offer", "chain": "base", "protocol_address": "0x0000000000000068f116a894984e2db1123eb395", "start_date": 1729692707, "expiration_date": 1729694207, "asset": null, "quantity": 4, "maker": "0xd4f4f6a1f386e041984da38e7be351903c767c2d", "taker": "", "payment": {"quantity": "4000000000000000", "token_address": "0x4200000000000000000000000000000000000006", "decimals": 18, "symbol": "WETH"}, "criteria": {"collection": {"slug": "boredape-baseclub"}, "contract": {"address": "0x0be0bb1097f4465b17b1ac3b22b5427d9cbf6d2c"}, "trait": null, "encoded_token_ids": null}, "event_timestamp": 1729692709, "is_private_listing": false}, {"event_type": "order", "order_hash": "0x438ed31be706128c346e044c6a9049459182af9f018df27dbda6450589fe3d04", "order_type": "collection_offer", "chain": "base", "protocol_address": "0x0000000000000068f116a894984e2db1123eb395", "start_date": 1729692704, "expiration_date": 1729694204, "asset": null, "quantity": 8, "maker": "0xd4f4f6a1f386e041984da38e7be351903c767c2d", "taker": "", "payment": {"quantity": "5600000000000000", "token_address": "0x4200000000000000000000000000000000000006", "decimals": 18, "symbol": "WETH"}, "criteria": {"collection": {"slug": "boredape-baseclub"}, "contract": {"address": "0x0be0bb1097f4465b17b1ac3b22b5427d9cbf6d2c"}, "trait": null, "encoded_token_ids": null}, "event_timestamp": 1729692706, "is_private_listing": false}, {"event_type": "order", "order_hash": "0x278722bf41ccac9542c4f44add5008083d3547042873f6efdac6ecf6574802fd", "order_type": "collection_offer", "chain": "base", "protocol_address": "0x0000000000000068f116a894984e2db1123eb395", "start_date": 1729692701, "expiration_date": 1729694201, "asset": null, "quantity": 20, "maker": "0xd4f4f6a1f386e041984da38e7be351903c767c2d", "taker": "", "payment": {"quantity": "4000000000000000", "token_address": "0x4200000000000000000000000000000000000006", "decimals": 18, "symbol": "WETH"}, "criteria": {"collection": {"slug": "boredape-baseclub"}, "contract": {"address": "0x0be0bb1097f4465b17b1ac3b22b5427d9cbf6d2c"}, "trait": null, "encoded_token_ids": null}, "event_timestamp": 1729692703, "is_private_listing": false}, {"event_type": "order", "order_hash": "0xb2d329a92fa5963fe596e259906c500af83aeccf710b8abdf651cd3ebb95d103", "order_type": "collection_offer", "chain": "base", "protocol_address": "0x0000000000000068f116a894984e2db1123eb395", "start_date": 1729691996, "expiration_date": 1729693496, "asset": null, "quantity": 4, "maker": "0xd4f4f6a1f386e041984da38e7be351903c767c2d", "taker": "", "payment": {"quantity": "4800000000000000", "token_address": "0x4200000000000000000000000000000000000006", "decimals": 18, "symbol": "WETH"}, "criteria": {"collection": {"slug": "boredape-baseclub"}, "contract": {"address": "0x0be0bb1097f4465b17b1ac3b22b5427d9cbf6d2c"}, "trait": null, "encoded_token_ids": null}, "event_timestamp": 1729691998, "is_private_listing": false}, {"event_type": "order", "order_hash": "0x1613d4429824b5d4cf9e86ecf9ae4364096559512cb08d79017df5166b50e304", "order_type": "collection_offer", "chain": "base", "protocol_address": "0x0000000000000068f116a894984e2db1123eb395", "start_date": 1729691993, "expiration_date": 1729693493, "asset": null, "quantity": 4, "maker": "0xd4f4f6a1f386e041984da38e7be351903c767c2d", "taker": "", "payment": {"quantity": "4000000000000000", "token_address": "0x4200000000000000000000000000000000000006", "decimals": 18, "symbol": "WETH"}, "criteria": {"collection": {"slug": "boredape-baseclub"}, "contract": {"address": "0x0be0bb1097f4465b17b1ac3b22b5427d9cbf6d2c"}, "trait": null, "encoded_token_ids": null}, "event_timestamp": 1729691995, "is_private_listing": false}, {"event_type": "order", "order_hash": "0xe279b6c95429ef23b38c9edc2d9be03ca8ca6e8b27efcde87685dc61a2ed7134", "order_type": "collection_offer", "chain": "base", "protocol_address": "0x0000000000000068f116a894984e2db1123eb395", "start_date": 1729691990, "expiration_date": 1729693489, "asset": null, "quantity": 8, "maker": "0xd4f4f6a1f386e041984da38e7be351903c767c2d", "taker": "", "payment": {"quantity": "5600000000000000", "token_address": "0x4200000000000000000000000000000000000006", "decimals": 18, "symbol": "WETH"}, "criteria": {"collection": {"slug": "boredape-baseclub"}, "contract": {"address": "0x0be0bb1097f4465b17b1ac3b22b5427d9cbf6d2c"}, "trait": null, "encoded_token_ids": null}, "event_timestamp": 1729691992, "is_private_listing": false}, {"event_type": "order", "order_hash": "0x3516a135922be741a460372670952507e84a77a89475ed878035359cb34a5116", "order_type": "collection_offer", "chain": "base", "protocol_address": "0x0000000000000068f116a894984e2db1123eb395", "start_date": 1729691986, "expiration_date": 1729693485, "asset": null, "quantity": 20, "maker": "0xd4f4f6a1f386e041984da38e7be351903c767c2d", "taker": "", "payment": {"quantity": "4000000000000000", "token_address": "0x4200000000000000000000000000000000000006", "decimals": 18, "symbol": "WETH"}, "criteria": {"collection": {"slug": "boredape-baseclub"}, "contract": {"address": "0x0be0bb1097f4465b17b1ac3b22b5427d9cbf6d2c"}, "trait": null, "encoded_token_ids": null}, "event_timestamp": 1729691988, "is_private_listing": false}, {"event_type": "order", "order_hash": "0xcd1132941f79f6fc66b31c7e8ccf25c6945e4a9d1b26c8d5f6668cde88a33b18", "order_type": "collection_offer", "chain": "base", "protocol_address": "0x0000000000000068f116a894984e2db1123eb395", "start_date": 1729691293, "expiration_date": 1729692793, "asset": null, "quantity": 4, "maker": "0xd4f4f6a1f386e041984da38e7be351903c767c2d", "taker": "", "payment": {"quantity": "4800000000000000", "token_address": "0x4200000000000000000000000000000000000006", "decimals": 18, "symbol": "WETH"}, "criteria": {"collection": {"slug": "boredape-baseclub"}, "contract": {"address": "0x0be0bb1097f4465b17b1ac3b22b5427d9cbf6d2c"}, "trait": null, "encoded_token_ids": null}, "event_timestamp": 1729691295, "is_private_listing": false}, {"event_type": "order", "order_hash": "0x34600d8accca1f30fc9668983753ee44c6f03ec806903a66f538051e084f66f9", "order_type": "collection_offer", "chain": "base", "protocol_address": "0x0000000000000068f116a894984e2db1123eb395", "start_date": 1729691290, "expiration_date": 1729692790, "asset": null, "quantity": 4, "maker": "0xd4f4f6a1f386e041984da38e7be351903c767c2d", "taker": "", "payment": {"quantity": "4000000000000000", "token_address": "0x4200000000000000000000000000000000000006", "decimals": 18, "symbol": "WETH"}, "criteria": {"collection": {"slug": "boredape-baseclub"}, "contract": {"address": "0x0be0bb1097f4465b17b1ac3b22b5427d9cbf6d2c"}, "trait": null, "encoded_token_ids": null}, "event_timestamp": 1729691292, "is_private_listing": false}, {"event_type": "order", "order_hash": "0xc06acf1d842bf25bc385e82d661e2a36210b1da9b849b79c108a9c074c489a04", "order_type": "collection_offer", "chain": "base", "protocol_address": "0x0000000000000068f116a894984e2db1123eb395", "start_date": 1729691287, "expiration_date": 1729692787, "asset": null, "quantity": 8, "maker": "0xd4f4f6a1f386e041984da38e7be351903c767c2d", "taker": "", "payment": {"quantity": "5600000000000000", "token_address": "0x4200000000000000000000000000000000000006", "decimals": 18, "symbol": "WETH"}, "criteria": {"collection": {"slug": "boredape-baseclub"}, "contract": {"address": "0x0be0bb1097f4465b17b1ac3b22b5427d9cbf6d2c"}, "trait": null, "encoded_token_ids": null}, "event_timestamp": 1729691289, "is_private_listing": false}, {"event_type": "order", "order_hash": "0x6986567baa877c7fe43ba92c8dd3e42600931eccb9a4bfad6a649e5939c19fbb", "order_type": "collection_offer", "chain": "base", "protocol_address": "0x0000000000000068f116a894984e2db1123eb395", "start_date": 1729691284, "expiration_date": 1729692784, "asset": null, "quantity": 20, "maker": "0xd4f4f6a1f386e041984da38e7be351903c767c2d", "taker": "", "payment": {"quantity": "4000000000000000", "token_address": "0x4200000000000000000000000000000000000006", "decimals": 18, "symbol": "WETH"}, "criteria": {"collection": {"slug": "boredape-baseclub"}, "contract": {"address": "0x0be0bb1097f4465b17b1ac3b22b5427d9cbf6d2c"}, "trait": null, "encoded_token_ids": null}, "event_timestamp": 1729691286, "is_private_listing": false}, {"event_type": "order", "order_hash": "0x6f0adf2f968c1341fdfc66aa8bcd432a332889e9d04d53bbe6f1e08f65970e02", "order_type": "collection_offer", "chain": "base", "protocol_address": "0x0000000000000068f116a894984e2db1123eb395", "start_date": 1729690589, "expiration_date": 1729692088, "asset": null, "quantity": 4, "maker": "0xd4f4f6a1f386e041984da38e7be351903c767c2d", "taker": "", "payment": {"quantity": "4800000000000000", "token_address": "0x4200000000000000000000000000000000000006", "decimals": 18, "symbol": "WETH"}, "criteria": {"collection": {"slug": "boredape-baseclub"}, "contract": {"address": "0x0be0bb1097f4465b17b1ac3b22b5427d9cbf6d2c"}, "trait": null, "encoded_token_ids": null}, "event_timestamp": 1729690591, "is_private_listing": false}, {"event_type": "order", "order_hash": "0x243e2abbf3d5b007cbe4204803ee9cdfb445f00acff587713fb8eca24777f611", "order_type": "collection_offer", "chain": "base", "protocol_address": "0x0000000000000068f116a894984e2db1123eb395", "start_date": 1729690585, "expiration_date": 1729692085, "asset": null, "quantity": 4, "maker": "0xd4f4f6a1f386e041984da38e7be351903c767c2d", "taker": "", "payment": {"quantity": "4000000000000000", "token_address": "0x4200000000000000000000000000000000000006", "decimals": 18, "symbol": "WETH"}, "criteria": {"collection": {"slug": "boredape-baseclub"}, "contract": {"address": "0x0be0bb1097f4465b17b1ac3b22b5427d9cbf6d2c"}, "trait": null, "encoded_token_ids": null}, "event_timestamp": 1729690587, "is_private_listing": false}, {"event_type": "order", "order_hash": "0xe262486351c042b101214b631595430fff580258ea857511a8b916ec00480408", "order_type": "collection_offer", "chain": "base", "protocol_address": "0x0000000000000068f116a894984e2db1123eb395", "start_date": 1729690581, "expiration_date": 1729692080, "asset": null, "quantity": 8, "maker": "0xd4f4f6a1f386e041984da38e7be351903c767c2d", "taker": "", "payment": {"quantity": "5600000000000000", "token_address": "0x4200000000000000000000000000000000000006", "decimals": 18, "symbol": "WETH"}, "criteria": {"collection": {"slug": "boredape-baseclub"}, "contract": {"address": "0x0be0bb1097f4465b17b1ac3b22b5427d9cbf6d2c"}, "trait": null, "encoded_token_ids": null}, "event_timestamp": 1729690584, "is_private_listing": false}, {"event_type": "order", "order_hash": "0xd263d8c1227d829c6c00b093bae90eacfb83ffcbf2e8375bcb3f28ac89914e33", "order_type": "collection_offer", "chain": "base", "protocol_address": "0x0000000000000068f116a894984e2db1123eb395", "start_date": 1729690577, "expiration_date": 1729692076, "asset": null, "quantity": 20, "maker": "0xd4f4f6a1f386e041984da38e7be351903c767c2d", "taker": "", "payment": {"quantity": "4000000000000000", "token_address": "0x4200000000000000000000000000000000000006", "decimals": 18, "symbol": "WETH"}, "criteria": {"collection": {"slug": "boredape-baseclub"}, "contract": {"address": "0x0be0bb1097f4465b17b1ac3b22b5427d9cbf6d2c"}, "trait": null, "encoded_token_ids": null}, "event_timestamp": 1729690579, "is_private_listing": false}, {"event_type": "order", "order_hash": "0x72d42536041bdd03ece2106dc88ab0816f05fe11b926b05bbf34f67d628b5a36", "order_type": "collection_offer", "chain": "base", "protocol_address": "0x0000000000000068f116a894984e2db1123eb395", "start_date": 1729689871, "expiration_date": 1729691371, "asset": null, "quantity": 4, "maker": "0xd4f4f6a1f386e041984da38e7be351903c767c2d", "taker": "", "payment": {"quantity": "4800000000000000", "token_address": "0x4200000000000000000000000000000000000006", "decimals": 18, "symbol": "WETH"}, "criteria": {"collection": {"slug": "boredape-baseclub"}, "contract": {"address": "0x0be0bb1097f4465b17b1ac3b22b5427d9cbf6d2c"}, "trait": null, "encoded_token_ids": null}, "event_timestamp": 1729689873, "is_private_listing": false}, {"event_type": "order", "order_hash": "0xfface13591324c152f15662c4514edd450cb9a0eca678a850a7ae35cc146c59a", "order_type": "collection_offer", "chain": "base", "protocol_address": "0x0000000000000068f116a894984e2db1123eb395", "start_date": 1729689868, "expiration_date": 1729691367, "asset": null, "quantity": 4, "maker": "0xd4f4f6a1f386e041984da38e7be351903c767c2d", "taker": "", "payment": {"quantity": "4000000000000000", "token_address": "0x4200000000000000000000000000000000000006", "decimals": 18, "symbol": "WETH"}, "criteria": {"collection": {"slug": "boredape-baseclub"}, "contract": {"address": "0x0be0bb1097f4465b17b1ac3b22b5427d9cbf6d2c"}, "trait": null, "encoded_token_ids": null}, "event_timestamp": 1729689869, "is_private_listing": false}, {"event_type": "order", "order_hash": "0x8bdb991ccb8cf580289963b126ec9ffdc2ca7a5feb14cbfd62a6c9ae4ecad95c", "order_type": "collection_offer", "chain": "base", "protocol_address": "0x0000000000000068f116a894984e2db1123eb395", "start_date": 1729689864, "expiration_date": 1729691364, "asset": null, "quantity": 8, "maker": "0xd4f4f6a1f386e041984da38e7be351903c767c2d", "taker": "", "payment": {"quantity": "5600000000000000", "token_address": "0x4200000000000000000000000000000000000006", "decimals": 18, "symbol": "WETH"}, "criteria": {"collection": {"slug": "boredape-baseclub"}, "contract": {"address": "0x0be0bb1097f4465b17b1ac3b22b5427d9cbf6d2c"}, "trait": null, "encoded_token_ids": null}, "event_timestamp": 1729689866, "is_private_listing": false}, {"event_type": "order", "order_hash": "0x4546efe773b810e2de5ebbe0ad2f1653a3aa0cd56372b0723e3df078e0310197", "order_type": "collection_offer", "chain": "base", "protocol_address": "0x0000000000000068f116a894984e2db1123eb395", "start_date": 1729689861, "expiration_date": 1729691360, "asset": null, "quantity": 20, "maker": "0xd4f4f6a1f386e041984da38e7be351903c767c2d", "taker": "", "payment": {"quantity": "4000000000000000", "token_address": "0x4200000000000000000000000000000000000006", "decimals": 18, "symbol": "WETH"}, "criteria": {"collection": {"slug": "boredape-baseclub"}, "contract": {"address": "0x0be0bb1097f4465b17b1ac3b22b5427d9cbf6d2c"}, "trait": null, "encoded_token_ids": null}, "event_timestamp": 1729689863, "is_private_listing": false}, {"event_type": "order", "order_hash": "0x3f69db2a8bd26a8c30e81f648208cfb8a11ad78717346487ff1d6f15b4e51218", "order_type": "collection_offer", "chain": "base", "protocol_address": "0x0000000000000068f116a894984e2db1123eb395", "start_date": 1729689438, "expiration_date": 1730294235, "asset": null, "quantity": 3, "maker": "0x2888eecd915fbb6be65dac1d51cd48a340e3ab1f", "taker": "", "payment": {"quantity": "4800000000000000", "token_address": "0x4200000000000000000000000000000000000006", "decimals": 18, "symbol": "WETH"}, "criteria": {"collection": {"slug": "boredape-baseclub"}, "contract": {"address": "0x0be0bb1097f4465b17b1ac3b22b5427d9cbf6d2c"}, "trait": null, "encoded_token_ids": null}, "event_timestamp": 1729689441, "is_private_listing": false}, {"event_type": "order", "order_hash": "0x5f3d2c19a730d8867cf8b3ead934478ef98260c9a40efb83066690ab92e92939", "order_type": "collection_offer", "chain": "base", "protocol_address": "0x0000000000000068f116a894984e2db1123eb395", "start_date": 1729689431, "expiration_date": 1730294228, "asset": null, "quantity": 3, "maker": "0x2888eecd915fbb6be65dac1d51cd48a340e3ab1f", "taker": "", "payment": {"quantity": "4200000000000000", "token_address": "0x4200000000000000000000000000000000000006", "decimals": 18, "symbol": "WETH"}, "criteria": {"collection": {"slug": "boredape-baseclub"}, "contract": {"address": "0x0be0bb1097f4465b17b1ac3b22b5427d9cbf6d2c"}, "trait": null, "encoded_token_ids": null}, "event_timestamp": 1729689434, "is_private_listing": false}, {"event_type": "order", "order_hash": "0x9a670f015f973a42d9e3ca8edad82854bf04cd968ba63d2b8991de467c00cc97", "order_type": "collection_offer", "chain": "base", "protocol_address": "0x0000000000000068f116a894984e2db1123eb395", "start_date": 1729689424, "expiration_date": 1730294220, "asset": null, "quantity": 3, "maker": "0x2888eecd915fbb6be65dac1d51cd48a340e3ab1f", "taker": "", "payment": {"quantity": "4500000000000000", "token_address": "0x4200000000000000000000000000000000000006", "decimals": 18, "symbol": "WETH"}, "criteria": {"collection": {"slug": "boredape-baseclub"}, "contract": {"address": "0x0be0bb1097f4465b17b1ac3b22b5427d9cbf6d2c"}, "trait": null, "encoded_token_ids": null}, "event_timestamp": 1729689427, "is_private_listing": false}, {"event_type": "order", "order_hash": "0xd2d9ebc487268eb46bd41cae41d20fa56cf7a2ec677ffb7bff3eafcfa809076f", "order_type": "listing", "chain": "base", "protocol_address": "0x0000000000000068f116a894984e2db1123eb395", "start_date": 1729689186, "expiration_date": 1732367586, "asset": {"identifier": "8030", "collection": "boredape-baseclub", "contract": "0x0be0bb1097f4465b17b1ac3b22b5427d9cbf6d2c", "token_standard": "erc721", "name": "BABC #8030", "description": "Discover the world of the Bored Ape Base Club (BABC) at boredapebaseclub.com , your exclusive gateway to a vibrant community on the Base Chain. Offering more than mere ownership, BABC NFTs act as a passport to an elite club for members only. By acquiring a BABC NFT, you gain access to private events and a chance to secure special edition Bitcoin NFTs. Join our community and explore the exclusive benefits awaiting BABC NFT holders.", "image_url": "https://ipfs.io/ipfs/bafybeicumgzxkdtbru4vzfkunv52crohdbeifrvpib56qnzzijgfshxmju/8030", "display_image_url": "https://i.seadn.io/s/raw/files/ef9c2ad1f9eb861784603905246542bd.png?w=500&auto=format", "display_animation_url": null, "metadata_url": "https://ipfs.io/ipfs/bafybeiacrqba67k6p7vu523mnumu36a34hcanowg4axxl2z3yse6ot437y/8030", "opensea_url": "https://opensea.io/assets/base/0x0be0bb1097f4465b17b1ac3b22b5427d9cbf6d2c/8030", "updated_at": "2024-11-14T22:09:29.776784", "is_disabled": false, "is_nsfw": false}, "quantity": 1, "maker": "0x2888eecd915fbb6be65dac1d51cd48a340e3ab1f", "taker": "", "payment": {"quantity": "8500000000000000", "token_address": "0x0000000000000000000000000000000000000000", "decimals": 18, "symbol": "ETH"}, "criteria": {}, "event_timestamp": 1729689192, "is_private_listing": false}, {"event_type": "order", "order_hash": "0x45225a017587387b614b760eb56f17f0ac366be59bec32436ff16ba2b372187a", "order_type": "listing", "chain": "base", "protocol_address": "0x0000000000000068f116a894984e2db1123eb395", "start_date": 1729689176, "expiration_date": 1732367576, "asset": {"identifier": "3749", "collection": "boredape-baseclub", "contract": "0x0be0bb1097f4465b17b1ac3b22b5427d9cbf6d2c", "token_standard": "erc721", "name": "BABC #3749", "description": "Discover the world of the Bored Ape Base Club (BABC) at boredapebaseclub.com , your exclusive gateway to a vibrant community on the Base Chain. Offering more than mere ownership, BABC NFTs act as a passport to an elite club for members only. By acquiring a BABC NFT, you gain access to private events and a chance to secure special edition Bitcoin NFTs. Join our community and explore the exclusive benefits awaiting BABC NFT holders.", "image_url": "https://ipfs.io/ipfs/bafybeidib6ptpfn3ob74boydmjvcxkgwgionijrh25do46jrapl2wqcobi/3749", "display_image_url": "https://i.seadn.io/s/raw/files/51afefc81aac5629c2a32eca24dde00d.png?w=500&auto=format", "display_animation_url": null, "metadata_url": "https://ipfs.io/ipfs/bafybeiacrqba67k6p7vu523mnumu36a34hcanowg4axxl2z3yse6ot437y/3749", "opensea_url": "https://opensea.io/assets/base/0x0be0bb1097f4465b17b1ac3b22b5427d9cbf6d2c/3749", "updated_at": "2024-11-20T14:25:38.220342", "is_disabled": false, "is_nsfw": false}, "quantity": 1, "maker": "0x2888eecd915fbb6be65dac1d51cd48a340e3ab1f", "taker": "", "payment": {"quantity": "8800000000000000", "token_address": "0x0000000000000000000000000000000000000000", "decimals": 18, "symbol": "ETH"}, "criteria": {}, "event_timestamp": 1729689183, "is_private_listing": false}, {"event_type": "order", "order_hash": "0x7431d9a9609afc55b720761a53361396d89c999490d98f5c171555024c739bce", "order_type": "listing", "chain": "base", "protocol_address": "0x0000000000000068f116a894984e2db1123eb395", "start_date": 1729689168, "expiration_date": 1732367568, "asset": {"identifier": "3111", "collection": "boredape-baseclub", "contract": "0x0be0bb1097f4465b17b1ac3b22b5427d9cbf6d2c", "token_standard": "erc721", "name": "BABC #3111", "description": "Discover the world of the Bored Ape Base Club (BABC) at boredapebaseclub.com , your exclusive gateway to a vibrant community on the Base Chain. Offering more than mere ownership, BABC NFTs act as a passport to an elite club for members only. By acquiring a BABC NFT, you gain access to private events and a chance to secure special edition Bitcoin NFTs. Join our community and explore the exclusive benefits awaiting BABC NFT holders.", "image_url": "https://ipfs.io/ipfs/bafybeieflkqumcivqyqita4hrfymeo7ex43kgdwn3f6tvqrgildxb7qebi/3111", "display_image_url": "https://i.seadn.io/s/raw/files/7bac4566c9183905208fb5e14573e580.png?w=500&auto=format", "display_animation_url": null, "metadata_url": "https://ipfs.io/ipfs/bafybeiacrqba67k6p7vu523mnumu36a34hcanowg4axxl2z3yse6ot437y/3111", "opensea_url": "https://opensea.io/assets/base/0x0be0bb1097f4465b17b1ac3b22b5427d9cbf6d2c/3111", "updated_at": "2024-11-15T09:20:56.824984", "is_disabled": false, "is_nsfw": false}, "quantity": 1, "maker": "0x2888eecd915fbb6be65dac1d51cd48a340e3ab1f", "taker": "", "payment": {"quantity": "5000000000000000", "token_address": "0x0000000000000000000000000000000000000000", "decimals": 18, "symbol": "ETH"}, "criteria": {}, "event_timestamp": 1729689174, "is_private_listing": false}, {"event_type": "order", "order_hash": "0x90600ac723c619ba3e7fb9f1560a43584e32e8e26a9fb683044c634746e2127b", "order_type": "listing", "chain": "base", "protocol_address": "0x0000000000000068f116a894984e2db1123eb395", "start_date": 1729689161, "expiration_date": 1732367561, "asset": {"identifier": "2560", "collection": "boredape-baseclub", "contract": "0x0be0bb1097f4465b17b1ac3b22b5427d9cbf6d2c", "token_standard": "erc721", "name": "BABC #2560", "description": "Discover the world of the Bored Ape Base Club (BABC) at boredapebaseclub.com , your exclusive gateway to a vibrant community on the Base Chain. Offering more than mere ownership, BABC NFTs act as a passport to an elite club for members only. By acquiring a BABC NFT, you gain access to private events and a chance to secure special edition Bitcoin NFTs. Join our community and explore the exclusive benefits awaiting BABC NFT holders.", "image_url": "https://ipfs.io/ipfs/bafybeidkos7vbmer67i2d7dq67wtfmzd3dlgpujnx2cipse2dehe5xmu5a/2560", "display_image_url": "https://i.seadn.io/s/raw/files/b07ba6090e714bc0661cc1564c48c232.png?w=500&auto=format", "display_animation_url": null, "metadata_url": "https://ipfs.io/ipfs/bafybeiacrqba67k6p7vu523mnumu36a34hcanowg4axxl2z3yse6ot437y/2560", "opensea_url": "https://opensea.io/assets/base/0x0be0bb1097f4465b17b1ac3b22b5427d9cbf6d2c/2560", "updated_at": "2024-11-20T22:25:39.322070", "is_disabled": false, "is_nsfw": false}, "quantity": 1, "maker": "0x2888eecd915fbb6be65dac1d51cd48a340e3ab1f", "taker": "", "payment": {"quantity": "3200000000000000", "token_address": "0x0000000000000000000000000000000000000000", "decimals": 18, "symbol": "ETH"}, "criteria": {}, "event_timestamp": 1729689166, "is_private_listing": false}, {"event_type": "order", "order_hash": "0xd3305b154308a275522239786aecc2e02ad022962754a952693766cacf64f5e0", "order_type": "collection_offer", "chain": "base", "protocol_address": "0x0000000000000068f116a894984e2db1123eb395", "start_date": 1729689136, "expiration_date": 1729690636, "asset": null, "quantity": 4, "maker": "0xd4f4f6a1f386e041984da38e7be351903c767c2d", "taker": "", "payment": {"quantity": "4800000000000000", "token_address": "0x4200000000000000000000000000000000000006", "decimals": 18, "symbol": "WETH"}, "criteria": {"collection": {"slug": "boredape-baseclub"}, "contract": {"address": "0x0be0bb1097f4465b17b1ac3b22b5427d9cbf6d2c"}, "trait": null, "encoded_token_ids": null}, "event_timestamp": 1729689138, "is_private_listing": false}, {"event_type": "order", "order_hash": "0x8dacbbba768d58578207bdaeb9eda9521629a9de888f0f3c4bb6cf7293191ece", "order_type": "collection_offer", "chain": "base", "protocol_address": "0x0000000000000068f116a894984e2db1123eb395", "start_date": 1729689133, "expiration_date": 1729690633, "asset": null, "quantity": 4, "maker": "0xd4f4f6a1f386e041984da38e7be351903c767c2d", "taker": "", "payment": {"quantity": "4000000000000000", "token_address": "0x4200000000000000000000000000000000000006", "decimals": 18, "symbol": "WETH"}, "criteria": {"collection": {"slug": "boredape-baseclub"}, "contract": {"address": "0x0be0bb1097f4465b17b1ac3b22b5427d9cbf6d2c"}, "trait": null, "encoded_token_ids": null}, "event_timestamp": 1729689135, "is_private_listing": false}, {"event_type": "order", "order_hash": "0x824cebc7ecc6673b229fa373fe8ded8c3ee10e0cb54f0b17407ec98986a032e0", "order_type": "collection_offer", "chain": "base", "protocol_address": "0x0000000000000068f116a894984e2db1123eb395", "start_date": 1729689129, "expiration_date": 1729690629, "asset": null, "quantity": 8, "maker": "0xd4f4f6a1f386e041984da38e7be351903c767c2d", "taker": "", "payment": {"quantity": "5600000000000000", "token_address": "0x4200000000000000000000000000000000000006", "decimals": 18, "symbol": "WETH"}, "criteria": {"collection": {"slug": "boredape-baseclub"}, "contract": {"address": "0x0be0bb1097f4465b17b1ac3b22b5427d9cbf6d2c"}, "trait": null, "encoded_token_ids": null}, "event_timestamp": 1729689132, "is_private_listing": false}, {"event_type": "order", "order_hash": "0x9ea022bb19d3d8aa4a8c1418de5e287b4062b896abf611f5cec59ae8c72fce86", "order_type": "collection_offer", "chain": "base", "protocol_address": "0x0000000000000068f116a894984e2db1123eb395", "start_date": 1729689125, "expiration_date": 1729690625, "asset": null, "quantity": 20, "maker": "0xd4f4f6a1f386e041984da38e7be351903c767c2d", "taker": "", "payment": {"quantity": "4000000000000000", "token_address": "0x4200000000000000000000000000000000000006", "decimals": 18, "symbol": "WETH"}, "criteria": {"collection": {"slug": "boredape-baseclub"}, "contract": {"address": "0x0be0bb1097f4465b17b1ac3b22b5427d9cbf6d2c"}, "trait": null, "encoded_token_ids": null}, "event_timestamp": 1729689128, "is_private_listing": false}, {"event_type": "order", "order_hash": "0x66b9bf4ae3f380c8e6657b16c326ad53c3c85b31cf5392072e9cb25b50fd0caf", "order_type": "collection_offer", "chain": "base", "protocol_address": "0x0000000000000068f116a894984e2db1123eb395", "start_date": 1729688415, "expiration_date": 1729689915, "asset": null, "quantity": 4, "maker": "0xd4f4f6a1f386e041984da38e7be351903c767c2d", "taker": "", "payment": {"quantity": "4800000000000000", "token_address": "0x4200000000000000000000000000000000000006", "decimals": 18, "symbol": "WETH"}, "criteria": {"collection": {"slug": "boredape-baseclub"}, "contract": {"address": "0x0be0bb1097f4465b17b1ac3b22b5427d9cbf6d2c"}, "trait": null, "encoded_token_ids": null}, "event_timestamp": 1729688417, "is_private_listing": false}, {"event_type": "order", "order_hash": "0xf5463e054f94434883d4af994dd830b30334d8cbb7b67368893a4359fd2c9603", "order_type": "collection_offer", "chain": "base", "protocol_address": "0x0000000000000068f116a894984e2db1123eb395", "start_date": 1729688412, "expiration_date": 1729689912, "asset": null, "quantity": 4, "maker": "0xd4f4f6a1f386e041984da38e7be351903c767c2d", "taker": "", "payment": {"quantity": "4000000000000000", "token_address": "0x4200000000000000000000000000000000000006", "decimals": 18, "symbol": "WETH"}, "criteria": {"collection": {"slug": "boredape-baseclub"}, "contract": {"address": "0x0be0bb1097f4465b17b1ac3b22b5427d9cbf6d2c"}, "trait": null, "encoded_token_ids": null}, "event_timestamp": 1729688414, "is_private_listing": false}, {"event_type": "order", "order_hash": "0xacc592e650a76ba5f4458617994ce855d51dc17dbecbaecc7492b356ad779794", "order_type": "collection_offer", "chain": "base", "protocol_address": "0x0000000000000068f116a894984e2db1123eb395", "start_date": 1729688409, "expiration_date": 1729689909, "asset": null, "quantity": 8, "maker": "0xd4f4f6a1f386e041984da38e7be351903c767c2d", "taker": "", "payment": {"quantity": "5600000000000000", "token_address": "0x4200000000000000000000000000000000000006", "decimals": 18, "symbol": "WETH"}, "criteria": {"collection": {"slug": "boredape-baseclub"}, "contract": {"address": "0x0be0bb1097f4465b17b1ac3b22b5427d9cbf6d2c"}, "trait": null, "encoded_token_ids": null}, "event_timestamp": 1729688411, "is_private_listing": false}, {"event_type": "order", "order_hash": "0x0d7d3ac904da09e7bf5ed5295e6ebf73c402768c585185c8df27f11e3cb8a409", "order_type": "collection_offer", "chain": "base", "protocol_address": "0x0000000000000068f116a894984e2db1123eb395", "start_date": 1729688405, "expiration_date": 1729689905, "asset": null, "quantity": 20, "maker": "0xd4f4f6a1f386e041984da38e7be351903c767c2d", "taker": "", "payment": {"quantity": "4000000000000000", "token_address": "0x4200000000000000000000000000000000000006", "decimals": 18, "symbol": "WETH"}, "criteria": {"collection": {"slug": "boredape-baseclub"}, "contract": {"address": "0x0be0bb1097f4465b17b1ac3b22b5427d9cbf6d2c"}, "trait": null, "encoded_token_ids": null}, "event_timestamp": 1729688407, "is_private_listing": false}, {"event_type": "order", "order_hash": "0xdae13dea56fd604a778c01ca7296ccc99ef319dd03deaf67ff062bb3ce9a3579", "order_type": "collection_offer", "chain": "base", "protocol_address": "0x0000000000000068f116a894984e2db1123eb395", "start_date": 1729687673, "expiration_date": 1729689173, "asset": null, "quantity": 4, "maker": "0xd4f4f6a1f386e041984da38e7be351903c767c2d", "taker": "", "payment": {"quantity": "4800000000000000", "token_address": "0x4200000000000000000000000000000000000006", "decimals": 18, "symbol": "WETH"}, "criteria": {"collection": {"slug": "boredape-baseclub"}, "contract": {"address": "0x0be0bb1097f4465b17b1ac3b22b5427d9cbf6d2c"}, "trait": null, "encoded_token_ids": null}, "event_timestamp": 1729687675, "is_private_listing": false}, {"event_type": "order", "order_hash": "0x4f5469ffd3090e15a4b8ff66ea10d87bffe384fcf1498c0007a24791e99af818", "order_type": "collection_offer", "chain": "base", "protocol_address": "0x0000000000000068f116a894984e2db1123eb395", "start_date": 1729687670, "expiration_date": 1729689170, "asset": null, "quantity": 4, "maker": "0xd4f4f6a1f386e041984da38e7be351903c767c2d", "taker": "", "payment": {"quantity": "4000000000000000", "token_address": "0x4200000000000000000000000000000000000006", "decimals": 18, "symbol": "WETH"}, "criteria": {"collection": {"slug": "boredape-baseclub"}, "contract": {"address": "0x0be0bb1097f4465b17b1ac3b22b5427d9cbf6d2c"}, "trait": null, "encoded_token_ids": null}, "event_timestamp": 1729687672, "is_private_listing": false}, {"event_type": "order", "order_hash": "0xe8690b021da0b5e7c40c6fd81962c8a9bc5ffae074566c4e2c9bacdc07cefacd", "order_type": "collection_offer", "chain": "base", "protocol_address": "0x0000000000000068f116a894984e2db1123eb395", "start_date": 1729687666, "expiration_date": 1729689166, "asset": null, "quantity": 8, "maker": "0xd4f4f6a1f386e041984da38e7be351903c767c2d", "taker": "", "payment": {"quantity": "5600000000000000", "token_address": "0x4200000000000000000000000000000000000006", "decimals": 18, "symbol": "WETH"}, "criteria": {"collection": {"slug": "boredape-baseclub"}, "contract": {"address": "0x0be0bb1097f4465b17b1ac3b22b5427d9cbf6d2c"}, "trait": null, "encoded_token_ids": null}, "event_timestamp": 1729687669, "is_private_listing": false}, {"event_type": "order", "order_hash": "0x7930f546a2d328d0fe97f530ca8aa0ab0248890758c0459712f8832c26763af2", "order_type": "collection_offer", "chain": "base", "protocol_address": "0x0000000000000068f116a894984e2db1123eb395", "start_date": 1729687663, "expiration_date": 1729689163, "asset": null, "quantity": 20, "maker": "0xd4f4f6a1f386e041984da38e7be351903c767c2d", "taker": "", "payment": {"quantity": "4000000000000000", "token_address": "0x4200000000000000000000000000000000000006", "decimals": 18, "symbol": "WETH"}, "criteria": {"collection": {"slug": "boredape-baseclub"}, "contract": {"address": "0x0be0bb1097f4465b17b1ac3b22b5427d9cbf6d2c"}, "trait": null, "encoded_token_ids": null}, "event_timestamp": 1729687665, "is_private_listing": false}, {"event_type": "order", "order_hash": "0xc68309c46b72c12928b607ca15a68c102bf859e829f417f3dc987a97dfa32374", "order_type": "collection_offer", "chain": "base", "protocol_address": "0x0000000000000068f116a894984e2db1123eb395", "start_date": 1729686913, "expiration_date": 1729688413, "asset": null, "quantity": 4, "maker": "0xd4f4f6a1f386e041984da38e7be351903c767c2d", "taker": "", "payment": {"quantity": "4800000000000000", "token_address": "0x4200000000000000000000000000000000000006", "decimals": 18, "symbol": "WETH"}, "criteria": {"collection": {"slug": "boredape-baseclub"}, "contract": {"address": "0x0be0bb1097f4465b17b1ac3b22b5427d9cbf6d2c"}, "trait": null, "encoded_token_ids": null}, "event_timestamp": 1729686915, "is_private_listing": false}, {"event_type": "order", "order_hash": "0x46a1c30ad5de5c557189f11cc426890cbef6e47968963612704c21cab1acd788", "order_type": "collection_offer", "chain": "base", "protocol_address": "0x0000000000000068f116a894984e2db1123eb395", "start_date": 1729686910, "expiration_date": 1729688410, "asset": null, "quantity": 4, "maker": "0xd4f4f6a1f386e041984da38e7be351903c767c2d", "taker": "", "payment": {"quantity": "4000000000000000", "token_address": "0x4200000000000000000000000000000000000006", "decimals": 18, "symbol": "WETH"}, "criteria": {"collection": {"slug": "boredape-baseclub"}, "contract": {"address": "0x0be0bb1097f4465b17b1ac3b22b5427d9cbf6d2c"}, "trait": null, "encoded_token_ids": null}, "event_timestamp": 1729686912, "is_private_listing": false}, {"event_type": "order", "order_hash": "0x95f7af884d1a15c3ba0831bd7f8e94d98d315ba81dfbd71a1144bc490fbcc6d8", "order_type": "collection_offer", "chain": "base", "protocol_address": "0x0000000000000068f116a894984e2db1123eb395", "start_date": 1729686906, "expiration_date": 1729688406, "asset": null, "quantity": 8, "maker": "0xd4f4f6a1f386e041984da38e7be351903c767c2d", "taker": "", "payment": {"quantity": "5600000000000000", "token_address": "0x4200000000000000000000000000000000000006", "decimals": 18, "symbol": "WETH"}, "criteria": {"collection": {"slug": "boredape-baseclub"}, "contract": {"address": "0x0be0bb1097f4465b17b1ac3b22b5427d9cbf6d2c"}, "trait": null, "encoded_token_ids": null}, "event_timestamp": 1729686909, "is_private_listing": false}, {"event_type": "order", "order_hash": "0xa0d6f0da6f8d390fe78708d5ac4cc422e6d23716f5e5808bb84505405016cb49", "order_type": "collection_offer", "chain": "base", "protocol_address": "0x0000000000000068f116a894984e2db1123eb395", "start_date": 1729686902, "expiration_date": 1729688402, "asset": null, "quantity": 20, "maker": "0xd4f4f6a1f386e041984da38e7be351903c767c2d", "taker": "", "payment": {"quantity": "4000000000000000", "token_address": "0x4200000000000000000000000000000000000006", "decimals": 18, "symbol": "WETH"}, "criteria": {"collection": {"slug": "boredape-baseclub"}, "contract": {"address": "0x0be0bb1097f4465b17b1ac3b22b5427d9cbf6d2c"}, "trait": null, "encoded_token_ids": null}, "event_timestamp": 1729686904, "is_private_listing": false}, {"event_type": "order", "order_hash": "0x5cd97448e0c1a4e963366ddc35fa0ff6bc9b75ea05df62c316b349514cc982c3", "order_type": "collection_offer", "chain": "base", "protocol_address": "0x0000000000000068f116a894984e2db1123eb395", "start_date": 1729686199, "expiration_date": 1729687699, "asset": null, "quantity": 4, "maker": "0xd4f4f6a1f386e041984da38e7be351903c767c2d", "taker": "", "payment": {"quantity": "4800000000000000", "token_address": "0x4200000000000000000000000000000000000006", "decimals": 18, "symbol": "WETH"}, "criteria": {"collection": {"slug": "boredape-baseclub"}, "contract": {"address": "0x0be0bb1097f4465b17b1ac3b22b5427d9cbf6d2c"}, "trait": null, "encoded_token_ids": null}, "event_timestamp": 1729686201, "is_private_listing": false}, {"event_type": "order", "order_hash": "0xf4c1972349df8ed7086a55bd17f628836b68a1fd03f49e11195d2b31260392bb", "order_type": "collection_offer", "chain": "base", "protocol_address": "0x0000000000000068f116a894984e2db1123eb395", "start_date": 1729686196, "expiration_date": 1729687696, "asset": null, "quantity": 4, "maker": "0xd4f4f6a1f386e041984da38e7be351903c767c2d", "taker": "", "payment": {"quantity": "4000000000000000", "token_address": "0x4200000000000000000000000000000000000006", "decimals": 18, "symbol": "WETH"}, "criteria": {"collection": {"slug": "boredape-baseclub"}, "contract": {"address": "0x0be0bb1097f4465b17b1ac3b22b5427d9cbf6d2c"}, "trait": null, "encoded_token_ids": null}, "event_timestamp": 1729686198, "is_private_listing": false}, {"event_type": "order", "order_hash": "0x4777eebf795da98b040e6a83f1bcd3af330736bddf92183a76845dba5fcc7ec6", "order_type": "collection_offer", "chain": "base", "protocol_address": "0x0000000000000068f116a894984e2db1123eb395", "start_date": 1729686193, "expiration_date": 1729687693, "asset": null, "quantity": 8, "maker": "0xd4f4f6a1f386e041984da38e7be351903c767c2d", "taker": "", "payment": {"quantity": "5600000000000000", "token_address": "0x4200000000000000000000000000000000000006", "decimals": 18, "symbol": "WETH"}, "criteria": {"collection": {"slug": "boredape-baseclub"}, "contract": {"address": "0x0be0bb1097f4465b17b1ac3b22b5427d9cbf6d2c"}, "trait": null, "encoded_token_ids": null}, "event_timestamp": 1729686195, "is_private_listing": false}, {"event_type": "order", "order_hash": "0x8ef6ec39b0e468a23c67389d3132d92f110a2afc812f6857d8dfc3a438b23d82", "order_type": "collection_offer", "chain": "base", "protocol_address": "0x0000000000000068f116a894984e2db1123eb395", "start_date": 1729686190, "expiration_date": 1729687690, "asset": null, "quantity": 20, "maker": "0xd4f4f6a1f386e041984da38e7be351903c767c2d", "taker": "", "payment": {"quantity": "4000000000000000", "token_address": "0x4200000000000000000000000000000000000006", "decimals": 18, "symbol": "WETH"}, "criteria": {"collection": {"slug": "boredape-baseclub"}, "contract": {"address": "0x0be0bb1097f4465b17b1ac3b22b5427d9cbf6d2c"}, "trait": null, "encoded_token_ids": null}, "event_timestamp": 1729686192, "is_private_listing": false}, {"event_type": "order", "order_hash": "0x084d56e6aea9e93fb8f37de0e0f0440f49da926524051c2068440ffdf883925e", "order_type": "collection_offer", "chain": "base", "protocol_address": "0x0000000000000068f116a894984e2db1123eb395", "start_date": 1729685486, "expiration_date": 1729686986, "asset": null, "quantity": 4, "maker": "0xd4f4f6a1f386e041984da38e7be351903c767c2d", "taker": "", "payment": {"quantity": "4800000000000000", "token_address": "0x4200000000000000000000000000000000000006", "decimals": 18, "symbol": "WETH"}, "criteria": {"collection": {"slug": "boredape-baseclub"}, "contract": {"address": "0x0be0bb1097f4465b17b1ac3b22b5427d9cbf6d2c"}, "trait": null, "encoded_token_ids": null}, "event_timestamp": 1729685488, "is_private_listing": false}, {"event_type": "order", "order_hash": "0x2492e99c82c0e353f75f27700f58bee1fe0aa95b32114b6638db72526f55324b", "order_type": "collection_offer", "chain": "base", "protocol_address": "0x0000000000000068f116a894984e2db1123eb395", "start_date": 1729685483, "expiration_date": 1729686982, "asset": null, "quantity": 4, "maker": "0xd4f4f6a1f386e041984da38e7be351903c767c2d", "taker": "", "payment": {"quantity": "4000000000000000", "token_address": "0x4200000000000000000000000000000000000006", "decimals": 18, "symbol": "WETH"}, "criteria": {"collection": {"slug": "boredape-baseclub"}, "contract": {"address": "0x0be0bb1097f4465b17b1ac3b22b5427d9cbf6d2c"}, "trait": null, "encoded_token_ids": null}, "event_timestamp": 1729685484, "is_private_listing": false}, {"event_type": "order", "order_hash": "0x44e29350e7309279db633a2a8b61179f3c87df656a2923e4d1fb3285d0ca9c8f", "order_type": "collection_offer", "chain": "base", "protocol_address": "0x0000000000000068f116a894984e2db1123eb395", "start_date": 1729685479, "expiration_date": 1729686979, "asset": null, "quantity": 8, "maker": "0xd4f4f6a1f386e041984da38e7be351903c767c2d", "taker": "", "payment": {"quantity": "5600000000000000", "token_address": "0x4200000000000000000000000000000000000006", "decimals": 18, "symbol": "WETH"}, "criteria": {"collection": {"slug": "boredape-baseclub"}, "contract": {"address": "0x0be0bb1097f4465b17b1ac3b22b5427d9cbf6d2c"}, "trait": null, "encoded_token_ids": null}, "event_timestamp": 1729685481, "is_private_listing": false}, {"event_type": "order", "order_hash": "0xd0576aae98ebdc8372cafb26e9f1dbfb0d9344c8adb4d301775cc13ca42376be", "order_type": "collection_offer", "chain": "base", "protocol_address": "0x0000000000000068f116a894984e2db1123eb395", "start_date": 1729685476, "expiration_date": 1729686976, "asset": null, "quantity": 20, "maker": "0xd4f4f6a1f386e041984da38e7be351903c767c2d", "taker": "", "payment": {"quantity": "4000000000000000", "token_address": "0x4200000000000000000000000000000000000006", "decimals": 18, "symbol": "WETH"}, "criteria": {"collection": {"slug": "boredape-baseclub"}, "contract": {"address": "0x0be0bb1097f4465b17b1ac3b22b5427d9cbf6d2c"}, "trait": null, "encoded_token_ids": null}, "event_timestamp": 1729685478, "is_private_listing": false}, {"event_type": "order", "order_hash": "0xebb999661ec6adfc1f8bc47db7221f8a99f324097c2a2aee37a87af45ce6ff98", "order_type": "collection_offer", "chain": "base", "protocol_address": "0x0000000000000068f116a894984e2db1123eb395", "start_date": 1729684768, "expiration_date": 1729686268, "asset": null, "quantity": 4, "maker": "0xd4f4f6a1f386e041984da38e7be351903c767c2d", "taker": "", "payment": {"quantity": "4800000000000000", "token_address": "0x4200000000000000000000000000000000000006", "decimals": 18, "symbol": "WETH"}, "criteria": {"collection": {"slug": "boredape-baseclub"}, "contract": {"address": "0x0be0bb1097f4465b17b1ac3b22b5427d9cbf6d2c"}, "trait": null, "encoded_token_ids": null}, "event_timestamp": 1729684770, "is_private_listing": false}, {"event_type": "order", "order_hash": "0x2532e97fb94a6ad02b009c2fbb6b465acd5121d4e5e63214442e41ac76019f44", "order_type": "collection_offer", "chain": "base", "protocol_address": "0x0000000000000068f116a894984e2db1123eb395", "start_date": 1729684765, "expiration_date": 1729686265, "asset": null, "quantity": 4, "maker": "0xd4f4f6a1f386e041984da38e7be351903c767c2d", "taker": "", "payment": {"quantity": "4000000000000000", "token_address": "0x4200000000000000000000000000000000000006", "decimals": 18, "symbol": "WETH"}, "criteria": {"collection": {"slug": "boredape-baseclub"}, "contract": {"address": "0x0be0bb1097f4465b17b1ac3b22b5427d9cbf6d2c"}, "trait": null, "encoded_token_ids": null}, "event_timestamp": 1729684767, "is_private_listing": false}, {"event_type": "order", "order_hash": "0xca4292d13efda695af85e25b350e19ab04721cefdc82946e098cff0e9b31bb8a", "order_type": "collection_offer", "chain": "base", "protocol_address": "0x0000000000000068f116a894984e2db1123eb395", "start_date": 1729684762, "expiration_date": 1729686261, "asset": null, "quantity": 8, "maker": "0xd4f4f6a1f386e041984da38e7be351903c767c2d", "taker": "", "payment": {"quantity": "5600000000000000", "token_address": "0x4200000000000000000000000000000000000006", "decimals": 18, "symbol": "WETH"}, "criteria": {"collection": {"slug": "boredape-baseclub"}, "contract": {"address": "0x0be0bb1097f4465b17b1ac3b22b5427d9cbf6d2c"}, "trait": null, "encoded_token_ids": null}, "event_timestamp": 1729684764, "is_private_listing": false}, {"event_type": "order", "order_hash": "0x5d5c4b78bf84c145999131310c3886c8d837e118522c8c1cebac3a0fd959b28e", "order_type": "collection_offer", "chain": "base", "protocol_address": "0x0000000000000068f116a894984e2db1123eb395", "start_date": 1729684758, "expiration_date": 1729686258, "asset": null, "quantity": 20, "maker": "0xd4f4f6a1f386e041984da38e7be351903c767c2d", "taker": "", "payment": {"quantity": "4000000000000000", "token_address": "0x4200000000000000000000000000000000000006", "decimals": 18, "symbol": "WETH"}, "criteria": {"collection": {"slug": "boredape-baseclub"}, "contract": {"address": "0x0be0bb1097f4465b17b1ac3b22b5427d9cbf6d2c"}, "trait": null, "encoded_token_ids": null}, "event_timestamp": 1729684760, "is_private_listing": false}, {"event_type": "order", "order_hash": "0xd7e38bbab093751aa24654480fb45a4c76d2939c3254aa8f868deddbeaddc47a", "order_type": "collection_offer", "chain": "base", "protocol_address": "0x0000000000000068f116a894984e2db1123eb395", "start_date": 1729684049, "expiration_date": 1729685549, "asset": null, "quantity": 4, "maker": "0xd4f4f6a1f386e041984da38e7be351903c767c2d", "taker": "", "payment": {"quantity": "4800000000000000", "token_address": "0x4200000000000000000000000000000000000006", "decimals": 18, "symbol": "WETH"}, "criteria": {"collection": {"slug": "boredape-baseclub"}, "contract": {"address": "0x0be0bb1097f4465b17b1ac3b22b5427d9cbf6d2c"}, "trait": null, "encoded_token_ids": null}, "event_timestamp": 1729684051, "is_private_listing": false}, {"event_type": "order", "order_hash": "0xdb178a39a177dd33f5247bc164a5ce343d0737a368f04ca4432dc6533627987a", "order_type": "collection_offer", "chain": "base", "protocol_address": "0x0000000000000068f116a894984e2db1123eb395", "start_date": 1729684045, "expiration_date": 1729685545, "asset": null, "quantity": 4, "maker": "0xd4f4f6a1f386e041984da38e7be351903c767c2d", "taker": "", "payment": {"quantity": "4000000000000000", "token_address": "0x4200000000000000000000000000000000000006", "decimals": 18, "symbol": "WETH"}, "criteria": {"collection": {"slug": "boredape-baseclub"}, "contract": {"address": "0x0be0bb1097f4465b17b1ac3b22b5427d9cbf6d2c"}, "trait": null, "encoded_token_ids": null}, "event_timestamp": 1729684047, "is_private_listing": false}, {"event_type": "order", "order_hash": "0x4bfa1deab7eb4f97fdb6372294b946dde9b24bbf4ace7f2d6ac2a25babc9add2", "order_type": "collection_offer", "chain": "base", "protocol_address": "0x0000000000000068f116a894984e2db1123eb395", "start_date": 1729684042, "expiration_date": 1729685542, "asset": null, "quantity": 8, "maker": "0xd4f4f6a1f386e041984da38e7be351903c767c2d", "taker": "", "payment": {"quantity": "5600000000000000", "token_address": "0x4200000000000000000000000000000000000006", "decimals": 18, "symbol": "WETH"}, "criteria": {"collection": {"slug": "boredape-baseclub"}, "contract": {"address": "0x0be0bb1097f4465b17b1ac3b22b5427d9cbf6d2c"}, "trait": null, "encoded_token_ids": null}, "event_timestamp": 1729684044, "is_private_listing": false}, {"event_type": "order", "order_hash": "0xe1696e825a5eeb0ad2482aef454769f7162899bc38cc2c5f8cd5bf054ce3f3f4", "order_type": "collection_offer", "chain": "base", "protocol_address": "0x0000000000000068f116a894984e2db1123eb395", "start_date": 1729684039, "expiration_date": 1729685539, "asset": null, "quantity": 20, "maker": "0xd4f4f6a1f386e041984da38e7be351903c767c2d", "taker": "", "payment": {"quantity": "4000000000000000", "token_address": "0x4200000000000000000000000000000000000006", "decimals": 18, "symbol": "WETH"}, "criteria": {"collection": {"slug": "boredape-baseclub"}, "contract": {"address": "0x0be0bb1097f4465b17b1ac3b22b5427d9cbf6d2c"}, "trait": null, "encoded_token_ids": null}, "event_timestamp": 1729684041, "is_private_listing": false}, {"event_type": "order", "order_hash": "0xe057ea70c38e571fd8fa79efcea1e71dd4c3b1a9f168da000b999806e9e6d771", "order_type": "collection_offer", "chain": "base", "protocol_address": "0x0000000000000068f116a894984e2db1123eb395", "start_date": 1729683303, "expiration_date": 1729684803, "asset": null, "quantity": 4, "maker": "0xd4f4f6a1f386e041984da38e7be351903c767c2d", "taker": "", "payment": {"quantity": "4800000000000000", "token_address": "0x4200000000000000000000000000000000000006", "decimals": 18, "symbol": "WETH"}, "criteria": {"collection": {"slug": "boredape-baseclub"}, "contract": {"address": "0x0be0bb1097f4465b17b1ac3b22b5427d9cbf6d2c"}, "trait": null, "encoded_token_ids": null}, "event_timestamp": 1729683305, "is_private_listing": false}, {"event_type": "order", "order_hash": "0xe89386e12c7970b562957f7864094985ef130555bbf501fdeb7a28bdb2a59b5f", "order_type": "collection_offer", "chain": "base", "protocol_address": "0x0000000000000068f116a894984e2db1123eb395", "start_date": 1729683300, "expiration_date": 1729684800, "asset": null, "quantity": 4, "maker": "0xd4f4f6a1f386e041984da38e7be351903c767c2d", "taker": "", "payment": {"quantity": "4000000000000000", "token_address": "0x4200000000000000000000000000000000000006", "decimals": 18, "symbol": "WETH"}, "criteria": {"collection": {"slug": "boredape-baseclub"}, "contract": {"address": "0x0be0bb1097f4465b17b1ac3b22b5427d9cbf6d2c"}, "trait": null, "encoded_token_ids": null}, "event_timestamp": 1729683302, "is_private_listing": false}, {"event_type": "order", "order_hash": "0x4e14f78d4342ccdeff26ac9aea5f5db9cad896c172525ebd520c9162c03207bf", "order_type": "collection_offer", "chain": "base", "protocol_address": "0x0000000000000068f116a894984e2db1123eb395", "start_date": 1729683297, "expiration_date": 1729684797, "asset": null, "quantity": 8, "maker": "0xd4f4f6a1f386e041984da38e7be351903c767c2d", "taker": "", "payment": {"quantity": "5600000000000000", "token_address": "0x4200000000000000000000000000000000000006", "decimals": 18, "symbol": "WETH"}, "criteria": {"collection": {"slug": "boredape-baseclub"}, "contract": {"address": "0x0be0bb1097f4465b17b1ac3b22b5427d9cbf6d2c"}, "trait": null, "encoded_token_ids": null}, "event_timestamp": 1729683299, "is_private_listing": false}, {"event_type": "order", "order_hash": "0xfdb9b1cdf2bf606b40f9bef724dd424b6ca8d21b547ba567d99677f49b7a58d5", "order_type": "collection_offer", "chain": "base", "protocol_address": "0x0000000000000068f116a894984e2db1123eb395", "start_date": 1729683294, "expiration_date": 1729684794, "asset": null, "quantity": 20, "maker": "0xd4f4f6a1f386e041984da38e7be351903c767c2d", "taker": "", "payment": {"quantity": "4000000000000000", "token_address": "0x4200000000000000000000000000000000000006", "decimals": 18, "symbol": "WETH"}, "criteria": {"collection": {"slug": "boredape-baseclub"}, "contract": {"address": "0x0be0bb1097f4465b17b1ac3b22b5427d9cbf6d2c"}, "trait": null, "encoded_token_ids": null}, "event_timestamp": 1729683295, "is_private_listing": false}, {"event_type": "order", "order_hash": "0x96e9d2b4e854edf7c4ce763991a3ac0d346b0c2753c8d37e05aad819cad0052d", "order_type": "collection_offer", "chain": "base", "protocol_address": "0x0000000000000068f116a894984e2db1123eb395", "start_date": 1729682575, "expiration_date": 1729684074, "asset": null, "quantity": 4, "maker": "0xd4f4f6a1f386e041984da38e7be351903c767c2d", "taker": "", "payment": {"quantity": "4800000000000000", "token_address": "0x4200000000000000000000000000000000000006", "decimals": 18, "symbol": "WETH"}, "criteria": {"collection": {"slug": "boredape-baseclub"}, "contract": {"address": "0x0be0bb1097f4465b17b1ac3b22b5427d9cbf6d2c"}, "trait": null, "encoded_token_ids": null}, "event_timestamp": 1729682577, "is_private_listing": false}, {"event_type": "order", "order_hash": "0xcd428a537a7deb174c824bb7dc07ab9acdd210490e9c30a22c6aec3d99bbeb95", "order_type": "collection_offer", "chain": "base", "protocol_address": "0x0000000000000068f116a894984e2db1123eb395", "start_date": 1729682571, "expiration_date": 1729684071, "asset": null, "quantity": 4, "maker": "0xd4f4f6a1f386e041984da38e7be351903c767c2d", "taker": "", "payment": {"quantity": "4000000000000000", "token_address": "0x4200000000000000000000000000000000000006", "decimals": 18, "symbol": "WETH"}, "criteria": {"collection": {"slug": "boredape-baseclub"}, "contract": {"address": "0x0be0bb1097f4465b17b1ac3b22b5427d9cbf6d2c"}, "trait": null, "encoded_token_ids": null}, "event_timestamp": 1729682573, "is_private_listing": false}, {"event_type": "order", "order_hash": "0xe6363bad7f87c01ea705881394d7032d4ab93423170401dc0cce69652190bad4", "order_type": "collection_offer", "chain": "base", "protocol_address": "0x0000000000000068f116a894984e2db1123eb395", "start_date": 1729682568, "expiration_date": 1729684067, "asset": null, "quantity": 8, "maker": "0xd4f4f6a1f386e041984da38e7be351903c767c2d", "taker": "", "payment": {"quantity": "5600000000000000", "token_address": "0x4200000000000000000000000000000000000006", "decimals": 18, "symbol": "WETH"}, "criteria": {"collection": {"slug": "boredape-baseclub"}, "contract": {"address": "0x0be0bb1097f4465b17b1ac3b22b5427d9cbf6d2c"}, "trait": null, "encoded_token_ids": null}, "event_timestamp": 1729682570, "is_private_listing": false}, {"event_type": "order", "order_hash": "0x4d5fb129a90501865d3f80ab42426ad98f81c2aa3bc4974ce86f163a48ba21e2", "order_type": "collection_offer", "chain": "base", "protocol_address": "0x0000000000000068f116a894984e2db1123eb395", "start_date": 1729682564, "expiration_date": 1729684064, "asset": null, "quantity": 20, "maker": "0xd4f4f6a1f386e041984da38e7be351903c767c2d", "taker": "", "payment": {"quantity": "4000000000000000", "token_address": "0x4200000000000000000000000000000000000006", "decimals": 18, "symbol": "WETH"}, "criteria": {"collection": {"slug": "boredape-baseclub"}, "contract": {"address": "0x0be0bb1097f4465b17b1ac3b22b5427d9cbf6d2c"}, "trait": null, "encoded_token_ids": null}, "event_timestamp": 1729682566, "is_private_listing": false}, {"event_type": "order", "order_hash": "0x020385e1bbd94b3b30ed568e6bf93fdd7c7eef49ff59170a9ef9b9a06aaf743f", "order_type": "collection_offer", "chain": "base", "protocol_address": "0x0000000000000068f116a894984e2db1123eb395", "start_date": 1729681852, "expiration_date": 1729683352, "asset": null, "quantity": 4, "maker": "0xd4f4f6a1f386e041984da38e7be351903c767c2d", "taker": "", "payment": {"quantity": "4800000000000000", "token_address": "0x4200000000000000000000000000000000000006", "decimals": 18, "symbol": "WETH"}, "criteria": {"collection": {"slug": "boredape-baseclub"}, "contract": {"address": "0x0be0bb1097f4465b17b1ac3b22b5427d9cbf6d2c"}, "trait": null, "encoded_token_ids": null}, "event_timestamp": 1729681854, "is_private_listing": false}, {"event_type": "order", "order_hash": "0xaf4c1a709eb675a9fb35d7f806ae8e19398d2960b912238a57fa270040e12a1e", "order_type": "collection_offer", "chain": "base", "protocol_address": "0x0000000000000068f116a894984e2db1123eb395", "start_date": 1729681849, "expiration_date": 1729683349, "asset": null, "quantity": 4, "maker": "0xd4f4f6a1f386e041984da38e7be351903c767c2d", "taker": "", "payment": {"quantity": "4000000000000000", "token_address": "0x4200000000000000000000000000000000000006", "decimals": 18, "symbol": "WETH"}, "criteria": {"collection": {"slug": "boredape-baseclub"}, "contract": {"address": "0x0be0bb1097f4465b17b1ac3b22b5427d9cbf6d2c"}, "trait": null, "encoded_token_ids": null}, "event_timestamp": 1729681851, "is_private_listing": false}, {"event_type": "order", "order_hash": "0x01ca53769efe500a4dbf3cb24521c28944955a4cc3831b36a2dcca3ef525ff46", "order_type": "collection_offer", "chain": "base", "protocol_address": "0x0000000000000068f116a894984e2db1123eb395", "start_date": 1729681846, "expiration_date": 1729683346, "asset": null, "quantity": 8, "maker": "0xd4f4f6a1f386e041984da38e7be351903c767c2d", "taker": "", "payment": {"quantity": "5600000000000000", "token_address": "0x4200000000000000000000000000000000000006", "decimals": 18, "symbol": "WETH"}, "criteria": {"collection": {"slug": "boredape-baseclub"}, "contract": {"address": "0x0be0bb1097f4465b17b1ac3b22b5427d9cbf6d2c"}, "trait": null, "encoded_token_ids": null}, "event_timestamp": 1729681848, "is_private_listing": false}, {"event_type": "order", "order_hash": "0x46d8178e07715d06cf0b2549a7f2d94531924a69f0827dc83b44b3f59ace03f4", "order_type": "collection_offer", "chain": "base", "protocol_address": "0x0000000000000068f116a894984e2db1123eb395", "start_date": 1729681842, "expiration_date": 1729683342, "asset": null, "quantity": 20, "maker": "0xd4f4f6a1f386e041984da38e7be351903c767c2d", "taker": "", "payment": {"quantity": "4000000000000000", "token_address": "0x4200000000000000000000000000000000000006", "decimals": 18, "symbol": "WETH"}, "criteria": {"collection": {"slug": "boredape-baseclub"}, "contract": {"address": "0x0be0bb1097f4465b17b1ac3b22b5427d9cbf6d2c"}, "trait": null, "encoded_token_ids": null}, "event_timestamp": 1729681845, "is_private_listing": false}]