[{"event_type": "order", "order_hash": "0xcad1bc228c44bdc5ad9c1c985da03fdc049df4de9ec703ba66c60537f451e789", "order_type": "listing", "chain": "base", "protocol_address": "0x0000000000000068f116a894984e2db1123eb395", "start_date": 1726769545, "expiration_date": 1726823545, "asset": {"identifier": "1488", "collection": "boredape-baseclub", "contract": "0x0be0bb1097f4465b17b1ac3b22b5427d9cbf6d2c", "token_standard": "erc721", "name": "BABC #1488", "description": "Discover the world of the Bored Ape Base Club (BABC) at boredapebaseclub.com , your exclusive gateway to a vibrant community on the Base Chain. Offering more than mere ownership, BABC NFTs act as a passport to an elite club for members only. By acquiring a BABC NFT, you gain access to private events and a chance to secure special edition Bitcoin NFTs. Join our community and explore the exclusive benefits awaiting BABC NFT holders.", "image_url": "https://ipfs.io/ipfs/bafybeihaue5tbwaisjlnkuneswhvv6qbmsimqgwee6xeejwc7hfenynwty/1488", "display_image_url": "https://i.seadn.io/s/raw/files/53b3773c48b6e3cc6331e89be8088809.png?w=500&auto=format", "display_animation_url": null, "metadata_url": "https://ipfs.io/ipfs/bafybeiacrqba67k6p7vu523mnumu36a34hcanowg4axxl2z3yse6ot437y/1488", "opensea_url": "https://opensea.io/assets/base/0x0be0bb1097f4465b17b1ac3b22b5427d9cbf6d2c/1488", "updated_at": "2024-10-23T10:38:42.475635", "is_disabled": false, "is_nsfw": false}, "quantity": 1, "maker": "0x1b5cbe0440861590ba929b2d0ef819a8f5f0d454", "taker": "", "payment": {"quantity": "1699999996000000", "token_address": "0x0000000000000000000000000000000000000000", "decimals": 18, "symbol": "ETH"}, "criteria": {}, "event_timestamp": 1726769547, "is_private_listing": false}, {"event_type": "order", "order_hash": "0x66b6a7b7d3f86cf038d8e25db4ac42b65041f27a8b8369d4d80782e284099517", "order_type": "collection_offer", "chain": "base", "protocol_address": "0x0000000000000068f116a894984e2db1123eb395", "start_date": 1726768925, "expiration_date": 1726770425, "asset": null, "quantity": 4, "maker": "0xd4f4f6a1f386e041984da38e7be351903c767c2d", "taker": "", "payment": {"quantity": "1200000000000000", "token_address": "0x4200000000000000000000000000000000000006", "decimals": 18, "symbol": "WETH"}, "criteria": {"collection": {"slug": "boredape-baseclub"}, "contract": {"address": "0x0be0bb1097f4465b17b1ac3b22b5427d9cbf6d2c"}, "trait": null, "encoded_token_ids": null}, "event_timestamp": 1726768927, "is_private_listing": false}, {"event_type": "order", "order_hash": "0x4b90524e9e89828e0d7eb39ecd00b3339f8beb39e8077105c0831c7062e40851", "order_type": "collection_offer", "chain": "base", "protocol_address": "0x0000000000000068f116a894984e2db1123eb395", "start_date": 1726768921, "expiration_date": 1726770421, "asset": null, "quantity": 6, "maker": "0xd4f4f6a1f386e041984da38e7be351903c767c2d", "taker": "", "payment": {"quantity": "1200000000000000", "token_address": "0x4200000000000000000000000000000000000006", "decimals": 18, "symbol": "WETH"}, "criteria": {"collection": {"slug": "boredape-baseclub"}, "contract": {"address": "0x0be0bb1097f4465b17b1ac3b22b5427d9cbf6d2c"}, "trait": null, "encoded_token_ids": null}, "event_timestamp": 1726768923, "is_private_listing": false}, {"event_type": "order", "order_hash": "0xaaa6dbb0db9e6d7b4045521394d539ca6cf4089f56afb8494884608132f912c4", "order_type": "listing", "chain": "base", "protocol_address": "0x0000000000000068f116a894984e2db1123eb395", "start_date": 1726768169, "expiration_date": 1729354855, "asset": {"identifier": "5533", "collection": "boredape-baseclub", "contract": "0x0be0bb1097f4465b17b1ac3b22b5427d9cbf6d2c", "token_standard": "erc721", "name": "BABC #5533", "description": "Discover the world of the Bored Ape Base Club (BABC) at boredapebaseclub.com , your exclusive gateway to a vibrant community on the Base Chain. Offering more than mere ownership, BABC NFTs act as a passport to an elite club for members only. By acquiring a BABC NFT, you gain access to private events and a chance to secure special edition Bitcoin NFTs. Join our community and explore the exclusive benefits awaiting BABC NFT holders.", "image_url": "https://ipfs.io/ipfs/bafybeiah3kgatq2d4ibjslxfogd4qbws5idwvzagmayu3nm6llxsz6si4q/5533", "display_image_url": "https://i.seadn.io/s/raw/files/ad2f80b106dcb1a09fc286c826fc7d40.png?w=500&auto=format", "display_animation_url": null, "metadata_url": "https://ipfs.io/ipfs/bafybeiacrqba67k6p7vu523mnumu36a34hcanowg4axxl2z3yse6ot437y/5533", "opensea_url": "https://opensea.io/assets/base/0x0be0bb1097f4465b17b1ac3b22b5427d9cbf6d2c/5533", "updated_at": "2024-10-06T22:41:55.978626", "is_disabled": false, "is_nsfw": false}, "quantity": 1, "maker": "0x99d98afead534d497a803fd4fb3f894eb775a74a", "taker": "", "payment": {"quantity": "1699999997000000", "token_address": "0x0000000000000000000000000000000000000000", "decimals": 18, "symbol": "ETH"}, "criteria": {}, "event_timestamp": 1726768190, "is_private_listing": false}, {"event_type": "order", "order_hash": "0x69437c6ce1e035a4e4c544e749314e9a9dde27855f452c433e2b0db557d09b24", "order_type": "collection_offer", "chain": "base", "protocol_address": "0x0000000000000068f116a894984e2db1123eb395", "start_date": 1726768108, "expiration_date": 1726769608, "asset": null, "quantity": 4, "maker": "0xd4f4f6a1f386e041984da38e7be351903c767c2d", "taker": "", "payment": {"quantity": "1200000000000000", "token_address": "0x4200000000000000000000000000000000000006", "decimals": 18, "symbol": "WETH"}, "criteria": {"collection": {"slug": "boredape-baseclub"}, "contract": {"address": "0x0be0bb1097f4465b17b1ac3b22b5427d9cbf6d2c"}, "trait": null, "encoded_token_ids": null}, "event_timestamp": 1726768110, "is_private_listing": false}, {"event_type": "order", "order_hash": "0xe77ff9c8ecfe1295a988caf598c97e2492ec718519d435bf8b58099546f60b21", "order_type": "collection_offer", "chain": "base", "protocol_address": "0x0000000000000068f116a894984e2db1123eb395", "start_date": 1726768105, "expiration_date": 1726769605, "asset": null, "quantity": 6, "maker": "0xd4f4f6a1f386e041984da38e7be351903c767c2d", "taker": "", "payment": {"quantity": "1200000000000000", "token_address": "0x4200000000000000000000000000000000000006", "decimals": 18, "symbol": "WETH"}, "criteria": {"collection": {"slug": "boredape-baseclub"}, "contract": {"address": "0x0be0bb1097f4465b17b1ac3b22b5427d9cbf6d2c"}, "trait": null, "encoded_token_ids": null}, "event_timestamp": 1726768107, "is_private_listing": false}, {"event_type": "order", "order_hash": "0xeb9986b523b16ebf7ee18e22ebcddc65881f8bd692076ce2c667242a7230de75", "order_type": "collection_offer", "chain": "base", "protocol_address": "0x0000000000000068f116a894984e2db1123eb395", "start_date": 1726767299, "expiration_date": 1726768799, "asset": null, "quantity": 4, "maker": "0xd4f4f6a1f386e041984da38e7be351903c767c2d", "taker": "", "payment": {"quantity": "1200000000000000", "token_address": "0x4200000000000000000000000000000000000006", "decimals": 18, "symbol": "WETH"}, "criteria": {"collection": {"slug": "boredape-baseclub"}, "contract": {"address": "0x0be0bb1097f4465b17b1ac3b22b5427d9cbf6d2c"}, "trait": null, "encoded_token_ids": null}, "event_timestamp": 1726767302, "is_private_listing": false}, {"event_type": "order", "order_hash": "0x3cbba782ae028e6f6c5b1ddd656f5bf13a57ebce377bbe5cda1f7846f26c7e4a", "order_type": "collection_offer", "chain": "base", "protocol_address": "0x0000000000000068f116a894984e2db1123eb395", "start_date": 1726767296, "expiration_date": 1726768796, "asset": null, "quantity": 6, "maker": "0xd4f4f6a1f386e041984da38e7be351903c767c2d", "taker": "", "payment": {"quantity": "1200000000000000", "token_address": "0x4200000000000000000000000000000000000006", "decimals": 18, "symbol": "WETH"}, "criteria": {"collection": {"slug": "boredape-baseclub"}, "contract": {"address": "0x0be0bb1097f4465b17b1ac3b22b5427d9cbf6d2c"}, "trait": null, "encoded_token_ids": null}, "event_timestamp": 1726767298, "is_private_listing": false}, {"event_type": "order", "order_hash": "0x5ebdd58c18c2b4947d34af0e3bd45ca2e2e390e8198da83be4c87cba48b8b7fa", "order_type": "collection_offer", "chain": "base", "protocol_address": "0x0000000000000068f116a894984e2db1123eb395", "start_date": 1726766465, "expiration_date": 1726767965, "asset": null, "quantity": 4, "maker": "0xd4f4f6a1f386e041984da38e7be351903c767c2d", "taker": "", "payment": {"quantity": "1200000000000000", "token_address": "0x4200000000000000000000000000000000000006", "decimals": 18, "symbol": "WETH"}, "criteria": {"collection": {"slug": "boredape-baseclub"}, "contract": {"address": "0x0be0bb1097f4465b17b1ac3b22b5427d9cbf6d2c"}, "trait": null, "encoded_token_ids": null}, "event_timestamp": 1726766467, "is_private_listing": false}, {"event_type": "order", "order_hash": "0x80f65c5ce17578dcb984fb7820505e7e177b46b59efffd0c8dfb0c05f9e39055", "order_type": "collection_offer", "chain": "base", "protocol_address": "0x0000000000000068f116a894984e2db1123eb395", "start_date": 1726766462, "expiration_date": 1726767962, "asset": null, "quantity": 6, "maker": "0xd4f4f6a1f386e041984da38e7be351903c767c2d", "taker": "", "payment": {"quantity": "1200000000000000", "token_address": "0x4200000000000000000000000000000000000006", "decimals": 18, "symbol": "WETH"}, "criteria": {"collection": {"slug": "boredape-baseclub"}, "contract": {"address": "0x0be0bb1097f4465b17b1ac3b22b5427d9cbf6d2c"}, "trait": null, "encoded_token_ids": null}, "event_timestamp": 1726766464, "is_private_listing": false}, {"event_type": "order", "order_hash": "0x0ac05d0332b65e87254bc3d1d3764da7cdb1dbf322a28370eddd34dc8cfe3425", "order_type": "collection_offer", "chain": "base", "protocol_address": "0x0000000000000068f116a894984e2db1123eb395", "start_date": 1726765638, "expiration_date": 1726767138, "asset": null, "quantity": 4, "maker": "0xd4f4f6a1f386e041984da38e7be351903c767c2d", "taker": "", "payment": {"quantity": "1200000000000000", "token_address": "0x4200000000000000000000000000000000000006", "decimals": 18, "symbol": "WETH"}, "criteria": {"collection": {"slug": "boredape-baseclub"}, "contract": {"address": "0x0be0bb1097f4465b17b1ac3b22b5427d9cbf6d2c"}, "trait": null, "encoded_token_ids": null}, "event_timestamp": 1726765640, "is_private_listing": false}, {"event_type": "order", "order_hash": "0xc59c71973ecd32606ab846a20e0373fc85377a01d818fe9f4a60a0d98cf7de62", "order_type": "collection_offer", "chain": "base", "protocol_address": "0x0000000000000068f116a894984e2db1123eb395", "start_date": 1726765635, "expiration_date": 1726767135, "asset": null, "quantity": 6, "maker": "0xd4f4f6a1f386e041984da38e7be351903c767c2d", "taker": "", "payment": {"quantity": "1200000000000000", "token_address": "0x4200000000000000000000000000000000000006", "decimals": 18, "symbol": "WETH"}, "criteria": {"collection": {"slug": "boredape-baseclub"}, "contract": {"address": "0x0be0bb1097f4465b17b1ac3b22b5427d9cbf6d2c"}, "trait": null, "encoded_token_ids": null}, "event_timestamp": 1726765637, "is_private_listing": false}, {"event_type": "order", "order_hash": "0xb8ce2a81c4f4d27243c508707b35f34f46c3909643fd61cc31b6289fdcffc8fa", "order_type": "collection_offer", "chain": "base", "protocol_address": "0x0000000000000068f116a894984e2db1123eb395", "start_date": 1726764804, "expiration_date": 1726766303, "asset": null, "quantity": 4, "maker": "0xd4f4f6a1f386e041984da38e7be351903c767c2d", "taker": "", "payment": {"quantity": "1200000000000000", "token_address": "0x4200000000000000000000000000000000000006", "decimals": 18, "symbol": "WETH"}, "criteria": {"collection": {"slug": "boredape-baseclub"}, "contract": {"address": "0x0be0bb1097f4465b17b1ac3b22b5427d9cbf6d2c"}, "trait": null, "encoded_token_ids": null}, "event_timestamp": 1726764805, "is_private_listing": false}, {"event_type": "order", "order_hash": "0xc1eb9c60237d90489459e17fd19900718f98e59fefdc4b07faed03d16943446e", "order_type": "collection_offer", "chain": "base", "protocol_address": "0x0000000000000068f116a894984e2db1123eb395", "start_date": 1726764800, "expiration_date": 1726766300, "asset": null, "quantity": 6, "maker": "0xd4f4f6a1f386e041984da38e7be351903c767c2d", "taker": "", "payment": {"quantity": "1200000000000000", "token_address": "0x4200000000000000000000000000000000000006", "decimals": 18, "symbol": "WETH"}, "criteria": {"collection": {"slug": "boredape-baseclub"}, "contract": {"address": "0x0be0bb1097f4465b17b1ac3b22b5427d9cbf6d2c"}, "trait": null, "encoded_token_ids": null}, "event_timestamp": 1726764802, "is_private_listing": false}, {"event_type": "order", "order_hash": "0xd82b1013eabefc7df83a9a872cfa636182c525ad46e97c813b7ab3a0edbdce36", "order_type": "collection_offer", "chain": "base", "protocol_address": "0x0000000000000068f116a894984e2db1123eb395", "start_date": 1726763958, "expiration_date": 1726765458, "asset": null, "quantity": 4, "maker": "0xd4f4f6a1f386e041984da38e7be351903c767c2d", "taker": "", "payment": {"quantity": "1200000000000000", "token_address": "0x4200000000000000000000000000000000000006", "decimals": 18, "symbol": "WETH"}, "criteria": {"collection": {"slug": "boredape-baseclub"}, "contract": {"address": "0x0be0bb1097f4465b17b1ac3b22b5427d9cbf6d2c"}, "trait": null, "encoded_token_ids": null}, "event_timestamp": 1726763960, "is_private_listing": false}, {"event_type": "order", "order_hash": "0x9d248249dea6483185014a3ab7ef2af92a6d668bacf4ce4a2cb79b02e9d8759e", "order_type": "collection_offer", "chain": "base", "protocol_address": "0x0000000000000068f116a894984e2db1123eb395", "start_date": 1726763955, "expiration_date": 1726765454, "asset": null, "quantity": 6, "maker": "0xd4f4f6a1f386e041984da38e7be351903c767c2d", "taker": "", "payment": {"quantity": "1200000000000000", "token_address": "0x4200000000000000000000000000000000000006", "decimals": 18, "symbol": "WETH"}, "criteria": {"collection": {"slug": "boredape-baseclub"}, "contract": {"address": "0x0be0bb1097f4465b17b1ac3b22b5427d9cbf6d2c"}, "trait": null, "encoded_token_ids": null}, "event_timestamp": 1726763957, "is_private_listing": false}, {"event_type": "order", "order_hash": "0xdfcc056f27bfcffaafc28e083c80375ac1ef65b51791882faa9e38eaa374570e", "order_type": "listing", "chain": "base", "protocol_address": "0x0000000000000068f116a894984e2db1123eb395", "start_date": 1726763533, "expiration_date": 1726817533, "asset": {"identifier": "6773", "collection": "boredape-baseclub", "contract": "0x0be0bb1097f4465b17b1ac3b22b5427d9cbf6d2c", "token_standard": "erc721", "name": "BABC #6773", "description": "Discover the world of the Bored Ape Base Club (BABC) at boredapebaseclub.com , your exclusive gateway to a vibrant community on the Base Chain. Offering more than mere ownership, BABC NFTs act as a passport to an elite club for members only. By acquiring a BABC NFT, you gain access to private events and a chance to secure special edition Bitcoin NFTs. Join our community and explore the exclusive benefits awaiting BABC NFT holders.", "image_url": "https://ipfs.io/ipfs/bafybeign2he4am27blezmaiioylryyb2gtqd6jddbctxeyx7a2zmmo5dyu/6773", "display_image_url": "https://i.seadn.io/s/raw/files/b4483a52d0a85aa6b5e9abf5a842c0d1.png?w=500&auto=format", "display_animation_url": null, "metadata_url": "https://ipfs.io/ipfs/bafybeiacrqba67k6p7vu523mnumu36a34hcanowg4axxl2z3yse6ot437y/6773", "opensea_url": "https://opensea.io/assets/base/0x0be0bb1097f4465b17b1ac3b22b5427d9cbf6d2c/6773", "updated_at": "2024-10-06T22:40:44.777301", "is_disabled": false, "is_nsfw": false}, "quantity": 1, "maker": "0x1b5cbe0440861590ba929b2d0ef819a8f5f0d454", "taker": "", "payment": {"quantity": "1699999998000000", "token_address": "0x0000000000000000000000000000000000000000", "decimals": 18, "symbol": "ETH"}, "criteria": {}, "event_timestamp": 1726763535, "is_private_listing": false}, {"event_type": "order", "order_hash": "0xe20d715670b4c21cc3018751fcafb7df55b72588bc7db848f9f10ed639338992", "order_type": "listing", "chain": "base", "protocol_address": "0x0000000000000068f116a894984e2db1123eb395", "start_date": 1726763527, "expiration_date": 1726817527, "asset": {"identifier": "2565", "collection": "boredape-baseclub", "contract": "0x0be0bb1097f4465b17b1ac3b22b5427d9cbf6d2c", "token_standard": "erc721", "name": "BABC #2565", "description": "Discover the world of the Bored Ape Base Club (BABC) at boredapebaseclub.com , your exclusive gateway to a vibrant community on the Base Chain. Offering more than mere ownership, BABC NFTs act as a passport to an elite club for members only. By acquiring a BABC NFT, you gain access to private events and a chance to secure special edition Bitcoin NFTs. Join our community and explore the exclusive benefits awaiting BABC NFT holders.", "image_url": "https://ipfs.io/ipfs/bafybeidkos7vbmer67i2d7dq67wtfmzd3dlgpujnx2cipse2dehe5xmu5a/2565", "display_image_url": "https://i.seadn.io/s/raw/files/30ee51cd880ee927b4b4d80facc17445.png?w=500&auto=format", "display_animation_url": null, "metadata_url": "https://ipfs.io/ipfs/bafybeiacrqba67k6p7vu523mnumu36a34hcanowg4axxl2z3yse6ot437y/2565", "opensea_url": "https://opensea.io/assets/base/0x0be0bb1097f4465b17b1ac3b22b5427d9cbf6d2c/2565", "updated_at": "2024-11-16T19:05:14.982676", "is_disabled": false, "is_nsfw": false}, "quantity": 1, "maker": "0x1b5cbe0440861590ba929b2d0ef819a8f5f0d454", "taker": "", "payment": {"quantity": "1699999998000000", "token_address": "0x0000000000000000000000000000000000000000", "decimals": 18, "symbol": "ETH"}, "criteria": {}, "event_timestamp": 1726763529, "is_private_listing": false}, {"event_type": "order", "order_hash": "0xffedc2e44bd8ac1cb4666f1d86c63a902fe2e165c44e2bc93ee86b971ed0c1a1", "order_type": "listing", "chain": "base", "protocol_address": "0x0000000000000068f116a894984e2db1123eb395", "start_date": 1726763520, "expiration_date": 1726817520, "asset": {"identifier": "1585", "collection": "boredape-baseclub", "contract": "0x0be0bb1097f4465b17b1ac3b22b5427d9cbf6d2c", "token_standard": "erc721", "name": "BABC #1585", "description": "Discover the world of the Bored Ape Base Club (BABC) at boredapebaseclub.com , your exclusive gateway to a vibrant community on the Base Chain. Offering more than mere ownership, BABC NFTs act as a passport to an elite club for members only. By acquiring a BABC NFT, you gain access to private events and a chance to secure special edition Bitcoin NFTs. Join our community and explore the exclusive benefits awaiting BABC NFT holders.", "image_url": "https://ipfs.io/ipfs/bafybeihaue5tbwaisjlnkuneswhvv6qbmsimqgwee6xeejwc7hfenynwty/1585", "display_image_url": "https://i.seadn.io/s/raw/files/5f79b139d5b1cc7501ab461e24827216.png?w=500&auto=format", "display_animation_url": null, "metadata_url": "https://ipfs.io/ipfs/bafybeiacrqba67k6p7vu523mnumu36a34hcanowg4axxl2z3yse6ot437y/1585", "opensea_url": "https://opensea.io/assets/base/0x0be0bb1097f4465b17b1ac3b22b5427d9cbf6d2c/1585", "updated_at": "2024-10-06T22:41:54.437109", "is_disabled": false, "is_nsfw": false}, "quantity": 1, "maker": "0x1b5cbe0440861590ba929b2d0ef819a8f5f0d454", "taker": "", "payment": {"quantity": "1699999998000000", "token_address": "0x0000000000000000000000000000000000000000", "decimals": 18, "symbol": "ETH"}, "criteria": {}, "event_timestamp": 1726763522, "is_private_listing": false}, {"event_type": "order", "order_hash": "0xa1fd4fa24b9612832c746e24a61051f0b0c52e5a84d4e196dbb7960706120e27", "order_type": "listing", "chain": "base", "protocol_address": "0x0000000000000068f116a894984e2db1123eb395", "start_date": 1726763514, "expiration_date": 1726817514, "asset": {"identifier": "1488", "collection": "boredape-baseclub", "contract": "0x0be0bb1097f4465b17b1ac3b22b5427d9cbf6d2c", "token_standard": "erc721", "name": "BABC #1488", "description": "Discover the world of the Bored Ape Base Club (BABC) at boredapebaseclub.com , your exclusive gateway to a vibrant community on the Base Chain. Offering more than mere ownership, BABC NFTs act as a passport to an elite club for members only. By acquiring a BABC NFT, you gain access to private events and a chance to secure special edition Bitcoin NFTs. Join our community and explore the exclusive benefits awaiting BABC NFT holders.", "image_url": "https://ipfs.io/ipfs/bafybeihaue5tbwaisjlnkuneswhvv6qbmsimqgwee6xeejwc7hfenynwty/1488", "display_image_url": "https://i.seadn.io/s/raw/files/53b3773c48b6e3cc6331e89be8088809.png?w=500&auto=format", "display_animation_url": null, "metadata_url": "https://ipfs.io/ipfs/bafybeiacrqba67k6p7vu523mnumu36a34hcanowg4axxl2z3yse6ot437y/1488", "opensea_url": "https://opensea.io/assets/base/0x0be0bb1097f4465b17b1ac3b22b5427d9cbf6d2c/1488", "updated_at": "2024-10-23T10:38:42.475635", "is_disabled": false, "is_nsfw": false}, "quantity": 1, "maker": "0x1b5cbe0440861590ba929b2d0ef819a8f5f0d454", "taker": "", "payment": {"quantity": "1699999998000000", "token_address": "0x0000000000000000000000000000000000000000", "decimals": 18, "symbol": "ETH"}, "criteria": {}, "event_timestamp": 1726763515, "is_private_listing": false}, {"event_type": "order", "order_hash": "0x4ad2d857d8adb898a542242068122f14c5acbd58795d3a2d2edcdc2353766931", "order_type": "collection_offer", "chain": "base", "protocol_address": "0x0000000000000068f116a894984e2db1123eb395", "start_date": 1726763031, "expiration_date": 1726764531, "asset": null, "quantity": 4, "maker": "0xd4f4f6a1f386e041984da38e7be351903c767c2d", "taker": "", "payment": {"quantity": "1200000000000000", "token_address": "0x4200000000000000000000000000000000000006", "decimals": 18, "symbol": "WETH"}, "criteria": {"collection": {"slug": "boredape-baseclub"}, "contract": {"address": "0x0be0bb1097f4465b17b1ac3b22b5427d9cbf6d2c"}, "trait": null, "encoded_token_ids": null}, "event_timestamp": 1726763033, "is_private_listing": false}, {"event_type": "order", "order_hash": "0x6099b707f7f0c5ebc56b9f5c7fb303a9e404c0b772ef280265a00f97c1031282", "order_type": "collection_offer", "chain": "base", "protocol_address": "0x0000000000000068f116a894984e2db1123eb395", "start_date": 1726763027, "expiration_date": 1726764527, "asset": null, "quantity": 6, "maker": "0xd4f4f6a1f386e041984da38e7be351903c767c2d", "taker": "", "payment": {"quantity": "1200000000000000", "token_address": "0x4200000000000000000000000000000000000006", "decimals": 18, "symbol": "WETH"}, "criteria": {"collection": {"slug": "boredape-baseclub"}, "contract": {"address": "0x0be0bb1097f4465b17b1ac3b22b5427d9cbf6d2c"}, "trait": null, "encoded_token_ids": null}, "event_timestamp": 1726763030, "is_private_listing": false}, {"event_type": "order", "order_hash": "0xffd7f4504af9cacf26666cce9dbbcee240fc0e0a2549cbd574455ad9a1d03973", "order_type": "listing", "chain": "base", "protocol_address": "0x0000000000000068f116a894984e2db1123eb395", "start_date": 1726762855, "expiration_date": 1729354855, "asset": {"identifier": "5533", "collection": "boredape-baseclub", "contract": "0x0be0bb1097f4465b17b1ac3b22b5427d9cbf6d2c", "token_standard": "erc721", "name": "BABC #5533", "description": "Discover the world of the Bored Ape Base Club (BABC) at boredapebaseclub.com , your exclusive gateway to a vibrant community on the Base Chain. Offering more than mere ownership, BABC NFTs act as a passport to an elite club for members only. By acquiring a BABC NFT, you gain access to private events and a chance to secure special edition Bitcoin NFTs. Join our community and explore the exclusive benefits awaiting BABC NFT holders.", "image_url": "https://ipfs.io/ipfs/bafybeiah3kgatq2d4ibjslxfogd4qbws5idwvzagmayu3nm6llxsz6si4q/5533", "display_image_url": "https://i.seadn.io/s/raw/files/ad2f80b106dcb1a09fc286c826fc7d40.png?w=500&auto=format", "display_animation_url": null, "metadata_url": "https://ipfs.io/ipfs/bafybeiacrqba67k6p7vu523mnumu36a34hcanowg4axxl2z3yse6ot437y/5533", "opensea_url": "https://opensea.io/assets/base/0x0be0bb1097f4465b17b1ac3b22b5427d9cbf6d2c/5533", "updated_at": "2024-10-06T22:41:55.978626", "is_disabled": false, "is_nsfw": false}, "quantity": 1, "maker": "0x99d98afead534d497a803fd4fb3f894eb775a74a", "taker": "", "payment": {"quantity": "1699999999000000", "token_address": "0x0000000000000000000000000000000000000000", "decimals": 18, "symbol": "ETH"}, "criteria": {}, "event_timestamp": 1726762876, "is_private_listing": false}, {"event_type": "order", "order_hash": "0x7b54b3a41a417d3d3a0f95de45809455ed51216592567afc054b843393ed816a", "order_type": "collection_offer", "chain": "base", "protocol_address": "0x0000000000000068f116a894984e2db1123eb395", "start_date": 1726762213, "expiration_date": 1726763713, "asset": null, "quantity": 2, "maker": "0xd4f4f6a1f386e041984da38e7be351903c767c2d", "taker": "", "payment": {"quantity": "1000000000000000", "token_address": "0x4200000000000000000000000000000000000006", "decimals": 18, "symbol": "WETH"}, "criteria": {"collection": {"slug": "boredape-baseclub"}, "contract": {"address": "0x0be0bb1097f4465b17b1ac3b22b5427d9cbf6d2c"}, "trait": null, "encoded_token_ids": null}, "event_timestamp": 1726762215, "is_private_listing": false}, {"event_type": "order", "order_hash": "0xb698b3e015d19319c20fd9ee633399d6f0eea1dd15374575dffb5b894c5d2202", "order_type": "collection_offer", "chain": "base", "protocol_address": "0x0000000000000068f116a894984e2db1123eb395", "start_date": 1726762210, "expiration_date": 1726763710, "asset": null, "quantity": 4, "maker": "0xd4f4f6a1f386e041984da38e7be351903c767c2d", "taker": "", "payment": {"quantity": "1600000000000000", "token_address": "0x4200000000000000000000000000000000000006", "decimals": 18, "symbol": "WETH"}, "criteria": {"collection": {"slug": "boredape-baseclub"}, "contract": {"address": "0x0be0bb1097f4465b17b1ac3b22b5427d9cbf6d2c"}, "trait": null, "encoded_token_ids": null}, "event_timestamp": 1726762212, "is_private_listing": false}, {"event_type": "order", "order_hash": "0xc3fd44e37e7717fbd8488841773a8a95876d97d332e355f6589a27864963118d", "order_type": "collection_offer", "chain": "base", "protocol_address": "0x0000000000000068f116a894984e2db1123eb395", "start_date": 1726762207, "expiration_date": 1726763707, "asset": null, "quantity": 6, "maker": "0xd4f4f6a1f386e041984da38e7be351903c767c2d", "taker": "", "payment": {"quantity": "1200000000000000", "token_address": "0x4200000000000000000000000000000000000006", "decimals": 18, "symbol": "WETH"}, "criteria": {"collection": {"slug": "boredape-baseclub"}, "contract": {"address": "0x0be0bb1097f4465b17b1ac3b22b5427d9cbf6d2c"}, "trait": null, "encoded_token_ids": null}, "event_timestamp": 1726762209, "is_private_listing": false}, {"event_type": "order", "order_hash": "0x5116f6edc80893590a9032d90c513929bb2fe392f726f507fd59c18185eea1ef", "order_type": "collection_offer", "chain": "base", "protocol_address": "0x0000000000000068f116a894984e2db1123eb395", "start_date": 1726761451, "expiration_date": 1726762951, "asset": null, "quantity": 2, "maker": "0xd4f4f6a1f386e041984da38e7be351903c767c2d", "taker": "", "payment": {"quantity": "1000000000000000", "token_address": "0x4200000000000000000000000000000000000006", "decimals": 18, "symbol": "WETH"}, "criteria": {"collection": {"slug": "boredape-baseclub"}, "contract": {"address": "0x0be0bb1097f4465b17b1ac3b22b5427d9cbf6d2c"}, "trait": null, "encoded_token_ids": null}, "event_timestamp": 1726761454, "is_private_listing": false}, {"event_type": "order", "order_hash": "0xd80b9fcb28725e3e3be68c2b167b649b78d56a7951e253d53075683b6bf2c7a7", "order_type": "collection_offer", "chain": "base", "protocol_address": "0x0000000000000068f116a894984e2db1123eb395", "start_date": 1726761448, "expiration_date": 1726762947, "asset": null, "quantity": 4, "maker": "0xd4f4f6a1f386e041984da38e7be351903c767c2d", "taker": "", "payment": {"quantity": "1600000000000000", "token_address": "0x4200000000000000000000000000000000000006", "decimals": 18, "symbol": "WETH"}, "criteria": {"collection": {"slug": "boredape-baseclub"}, "contract": {"address": "0x0be0bb1097f4465b17b1ac3b22b5427d9cbf6d2c"}, "trait": null, "encoded_token_ids": null}, "event_timestamp": 1726761450, "is_private_listing": false}, {"event_type": "order", "order_hash": "0xe03ff99d2c41b73558d7df0c9c53e8e61c681361c05fdabbb3e0ae2779f68c40", "order_type": "collection_offer", "chain": "base", "protocol_address": "0x0000000000000068f116a894984e2db1123eb395", "start_date": 1726761444, "expiration_date": 1726762944, "asset": null, "quantity": 6, "maker": "0xd4f4f6a1f386e041984da38e7be351903c767c2d", "taker": "", "payment": {"quantity": "1200000000000000", "token_address": "0x4200000000000000000000000000000000000006", "decimals": 18, "symbol": "WETH"}, "criteria": {"collection": {"slug": "boredape-baseclub"}, "contract": {"address": "0x0be0bb1097f4465b17b1ac3b22b5427d9cbf6d2c"}, "trait": null, "encoded_token_ids": null}, "event_timestamp": 1726761446, "is_private_listing": false}, {"event_type": "order", "order_hash": "0x2f8bc3c22e8957745714dc94726cf4774bf7ea6b74c60f9614b6eec06c608780", "order_type": "collection_offer", "chain": "base", "protocol_address": "0x0000000000000068f116a894984e2db1123eb395", "start_date": 1726760666, "expiration_date": 1726762166, "asset": null, "quantity": 2, "maker": "0xd4f4f6a1f386e041984da38e7be351903c767c2d", "taker": "", "payment": {"quantity": "1000000000000000", "token_address": "0x4200000000000000000000000000000000000006", "decimals": 18, "symbol": "WETH"}, "criteria": {"collection": {"slug": "boredape-baseclub"}, "contract": {"address": "0x0be0bb1097f4465b17b1ac3b22b5427d9cbf6d2c"}, "trait": null, "encoded_token_ids": null}, "event_timestamp": 1726760668, "is_private_listing": false}, {"event_type": "order", "order_hash": "0x6f1d65a6d4d1a04511b2eba815d9a26c51fc56fccb36a574d5fca547f6fe7e4c", "order_type": "collection_offer", "chain": "base", "protocol_address": "0x0000000000000068f116a894984e2db1123eb395", "start_date": 1726760663, "expiration_date": 1726762163, "asset": null, "quantity": 4, "maker": "0xd4f4f6a1f386e041984da38e7be351903c767c2d", "taker": "", "payment": {"quantity": "1600000000000000", "token_address": "0x4200000000000000000000000000000000000006", "decimals": 18, "symbol": "WETH"}, "criteria": {"collection": {"slug": "boredape-baseclub"}, "contract": {"address": "0x0be0bb1097f4465b17b1ac3b22b5427d9cbf6d2c"}, "trait": null, "encoded_token_ids": null}, "event_timestamp": 1726760665, "is_private_listing": false}, {"event_type": "order", "order_hash": "0x7b724b6bec9f579c3e2f6f71083b8c389b8036b31ce64401277d00d059cfb14e", "order_type": "collection_offer", "chain": "base", "protocol_address": "0x0000000000000068f116a894984e2db1123eb395", "start_date": 1726760660, "expiration_date": 1726762160, "asset": null, "quantity": 6, "maker": "0xd4f4f6a1f386e041984da38e7be351903c767c2d", "taker": "", "payment": {"quantity": "1200000000000000", "token_address": "0x4200000000000000000000000000000000000006", "decimals": 18, "symbol": "WETH"}, "criteria": {"collection": {"slug": "boredape-baseclub"}, "contract": {"address": "0x0be0bb1097f4465b17b1ac3b22b5427d9cbf6d2c"}, "trait": null, "encoded_token_ids": null}, "event_timestamp": 1726760662, "is_private_listing": false}, {"event_type": "order", "order_hash": "0x7b8ed57b38e4a9ff09f7e27d43a8b986c49988637eae432869c745042854c9f9", "order_type": "collection_offer", "chain": "base", "protocol_address": "0x0000000000000068f116a894984e2db1123eb395", "start_date": 1726759926, "expiration_date": 1726761426, "asset": null, "quantity": 2, "maker": "0xd4f4f6a1f386e041984da38e7be351903c767c2d", "taker": "", "payment": {"quantity": "1000000000000000", "token_address": "0x4200000000000000000000000000000000000006", "decimals": 18, "symbol": "WETH"}, "criteria": {"collection": {"slug": "boredape-baseclub"}, "contract": {"address": "0x0be0bb1097f4465b17b1ac3b22b5427d9cbf6d2c"}, "trait": null, "encoded_token_ids": null}, "event_timestamp": 1726759928, "is_private_listing": false}, {"event_type": "order", "order_hash": "0x4d3658ed4cf5012f5576f148c39883841e5d11fbce09527ea1a359f901e180c3", "order_type": "collection_offer", "chain": "base", "protocol_address": "0x0000000000000068f116a894984e2db1123eb395", "start_date": 1726759923, "expiration_date": 1726761423, "asset": null, "quantity": 4, "maker": "0xd4f4f6a1f386e041984da38e7be351903c767c2d", "taker": "", "payment": {"quantity": "1600000000000000", "token_address": "0x4200000000000000000000000000000000000006", "decimals": 18, "symbol": "WETH"}, "criteria": {"collection": {"slug": "boredape-baseclub"}, "contract": {"address": "0x0be0bb1097f4465b17b1ac3b22b5427d9cbf6d2c"}, "trait": null, "encoded_token_ids": null}, "event_timestamp": 1726759925, "is_private_listing": false}, {"event_type": "order", "order_hash": "0x4eb4c9370fba3607981a9d93f3cabf87be0b1f599b2dc8c148eacb2709c3af83", "order_type": "collection_offer", "chain": "base", "protocol_address": "0x0000000000000068f116a894984e2db1123eb395", "start_date": 1726759919, "expiration_date": 1726761419, "asset": null, "quantity": 6, "maker": "0xd4f4f6a1f386e041984da38e7be351903c767c2d", "taker": "", "payment": {"quantity": "1200000000000000", "token_address": "0x4200000000000000000000000000000000000006", "decimals": 18, "symbol": "WETH"}, "criteria": {"collection": {"slug": "boredape-baseclub"}, "contract": {"address": "0x0be0bb1097f4465b17b1ac3b22b5427d9cbf6d2c"}, "trait": null, "encoded_token_ids": null}, "event_timestamp": 1726759921, "is_private_listing": false}, {"event_type": "order", "order_hash": "0xc6865b1fafa9f5d10d26dd66c382bbbac731606f9278d34e9255b98baf705833", "order_type": "collection_offer", "chain": "base", "protocol_address": "0x0000000000000068f116a894984e2db1123eb395", "start_date": 1726759150, "expiration_date": 1726760650, "asset": null, "quantity": 2, "maker": "0xd4f4f6a1f386e041984da38e7be351903c767c2d", "taker": "", "payment": {"quantity": "1000000000000000", "token_address": "0x4200000000000000000000000000000000000006", "decimals": 18, "symbol": "WETH"}, "criteria": {"collection": {"slug": "boredape-baseclub"}, "contract": {"address": "0x0be0bb1097f4465b17b1ac3b22b5427d9cbf6d2c"}, "trait": null, "encoded_token_ids": null}, "event_timestamp": 1726759152, "is_private_listing": false}, {"event_type": "order", "order_hash": "0x5b6305a077f0589888d3dfbe094c0d98f899f8d2a94a4de07feb8b166073fae3", "order_type": "collection_offer", "chain": "base", "protocol_address": "0x0000000000000068f116a894984e2db1123eb395", "start_date": 1726759147, "expiration_date": 1726760647, "asset": null, "quantity": 4, "maker": "0xd4f4f6a1f386e041984da38e7be351903c767c2d", "taker": "", "payment": {"quantity": "1600000000000000", "token_address": "0x4200000000000000000000000000000000000006", "decimals": 18, "symbol": "WETH"}, "criteria": {"collection": {"slug": "boredape-baseclub"}, "contract": {"address": "0x0be0bb1097f4465b17b1ac3b22b5427d9cbf6d2c"}, "trait": null, "encoded_token_ids": null}, "event_timestamp": 1726759149, "is_private_listing": false}, {"event_type": "order", "order_hash": "0x0d128082efda4632b1cfd402e1e602c6b5a2d35aa9663d4c2416e4419789b081", "order_type": "collection_offer", "chain": "base", "protocol_address": "0x0000000000000068f116a894984e2db1123eb395", "start_date": 1726759144, "expiration_date": 1726760644, "asset": null, "quantity": 6, "maker": "0xd4f4f6a1f386e041984da38e7be351903c767c2d", "taker": "", "payment": {"quantity": "1200000000000000", "token_address": "0x4200000000000000000000000000000000000006", "decimals": 18, "symbol": "WETH"}, "criteria": {"collection": {"slug": "boredape-baseclub"}, "contract": {"address": "0x0be0bb1097f4465b17b1ac3b22b5427d9cbf6d2c"}, "trait": null, "encoded_token_ids": null}, "event_timestamp": 1726759146, "is_private_listing": false}, {"event_type": "order", "order_hash": "0xe562fc842076e8f9a00c6fcf876f023ff4415fd4ea1c10df9d15bbcdc863913a", "order_type": "collection_offer", "chain": "base", "protocol_address": "0x0000000000000068f116a894984e2db1123eb395", "start_date": 1726758393, "expiration_date": 1726759893, "asset": null, "quantity": 2, "maker": "0xd4f4f6a1f386e041984da38e7be351903c767c2d", "taker": "", "payment": {"quantity": "1000000000000000", "token_address": "0x4200000000000000000000000000000000000006", "decimals": 18, "symbol": "WETH"}, "criteria": {"collection": {"slug": "boredape-baseclub"}, "contract": {"address": "0x0be0bb1097f4465b17b1ac3b22b5427d9cbf6d2c"}, "trait": null, "encoded_token_ids": null}, "event_timestamp": 1726758395, "is_private_listing": false}, {"event_type": "order", "order_hash": "0x0bd1738c4de91bbe07be19b1938b265209e117b24d34344a2ad1a5b238f437bc", "order_type": "collection_offer", "chain": "base", "protocol_address": "0x0000000000000068f116a894984e2db1123eb395", "start_date": 1726758390, "expiration_date": 1726759890, "asset": null, "quantity": 4, "maker": "0xd4f4f6a1f386e041984da38e7be351903c767c2d", "taker": "", "payment": {"quantity": "1600000000000000", "token_address": "0x4200000000000000000000000000000000000006", "decimals": 18, "symbol": "WETH"}, "criteria": {"collection": {"slug": "boredape-baseclub"}, "contract": {"address": "0x0be0bb1097f4465b17b1ac3b22b5427d9cbf6d2c"}, "trait": null, "encoded_token_ids": null}, "event_timestamp": 1726758392, "is_private_listing": false}, {"event_type": "order", "order_hash": "0xd834f761df7ccde7d1371c1d3dd8cd673a4a31ace46073917932e20273b46666", "order_type": "collection_offer", "chain": "base", "protocol_address": "0x0000000000000068f116a894984e2db1123eb395", "start_date": 1726758387, "expiration_date": 1726759886, "asset": null, "quantity": 6, "maker": "0xd4f4f6a1f386e041984da38e7be351903c767c2d", "taker": "", "payment": {"quantity": "1200000000000000", "token_address": "0x4200000000000000000000000000000000000006", "decimals": 18, "symbol": "WETH"}, "criteria": {"collection": {"slug": "boredape-baseclub"}, "contract": {"address": "0x0be0bb1097f4465b17b1ac3b22b5427d9cbf6d2c"}, "trait": null, "encoded_token_ids": null}, "event_timestamp": 1726758389, "is_private_listing": false}, {"event_type": "order", "order_hash": "0xe62c71bf86791c0d4152f6ef7df6e4277c5084b1bff8910c15ac2f388e188a11", "order_type": "collection_offer", "chain": "base", "protocol_address": "0x0000000000000068f116a894984e2db1123eb395", "start_date": 1726757873, "expiration_date": 1727362656, "asset": null, "quantity": 5, "maker": "0x8995c3bee9655f41dee4f34f9508a56589252f67", "taker": "", "payment": {"quantity": "5000000000000000", "token_address": "0x4200000000000000000000000000000000000006", "decimals": 18, "symbol": "WETH"}, "criteria": {"collection": {"slug": "boredape-baseclub"}, "contract": {"address": "0x0be0bb1097f4465b17b1ac3b22b5427d9cbf6d2c"}, "trait": null, "encoded_token_ids": null}, "event_timestamp": 1726757880, "is_private_listing": false}, {"event_type": "order", "order_hash": "0xfd8c546e66acec902b9adf47d3e79166684f153b3dd4457117b9d22843792d55", "order_type": "collection_offer", "chain": "base", "protocol_address": "0x0000000000000068f116a894984e2db1123eb395", "start_date": 1726757617, "expiration_date": 1726759116, "asset": null, "quantity": 2, "maker": "0xd4f4f6a1f386e041984da38e7be351903c767c2d", "taker": "", "payment": {"quantity": "1000000000000000", "token_address": "0x4200000000000000000000000000000000000006", "decimals": 18, "symbol": "WETH"}, "criteria": {"collection": {"slug": "boredape-baseclub"}, "contract": {"address": "0x0be0bb1097f4465b17b1ac3b22b5427d9cbf6d2c"}, "trait": null, "encoded_token_ids": null}, "event_timestamp": 1726757618, "is_private_listing": false}, {"event_type": "order", "order_hash": "0x615ccc240fdb56adc94962674e2d992623407e61945f53c6c3deb74964a94c36", "order_type": "collection_offer", "chain": "base", "protocol_address": "0x0000000000000068f116a894984e2db1123eb395", "start_date": 1726757613, "expiration_date": 1726759113, "asset": null, "quantity": 4, "maker": "0xd4f4f6a1f386e041984da38e7be351903c767c2d", "taker": "", "payment": {"quantity": "1600000000000000", "token_address": "0x4200000000000000000000000000000000000006", "decimals": 18, "symbol": "WETH"}, "criteria": {"collection": {"slug": "boredape-baseclub"}, "contract": {"address": "0x0be0bb1097f4465b17b1ac3b22b5427d9cbf6d2c"}, "trait": null, "encoded_token_ids": null}, "event_timestamp": 1726757615, "is_private_listing": false}, {"event_type": "order", "order_hash": "0xa56b97a1e8b6040c9ed167f1371c6f58412a8cacf6d2d17fd7f56b1378370aa9", "order_type": "collection_offer", "chain": "base", "protocol_address": "0x0000000000000068f116a894984e2db1123eb395", "start_date": 1726757610, "expiration_date": 1726759110, "asset": null, "quantity": 6, "maker": "0xd4f4f6a1f386e041984da38e7be351903c767c2d", "taker": "", "payment": {"quantity": "1200000000000000", "token_address": "0x4200000000000000000000000000000000000006", "decimals": 18, "symbol": "WETH"}, "criteria": {"collection": {"slug": "boredape-baseclub"}, "contract": {"address": "0x0be0bb1097f4465b17b1ac3b22b5427d9cbf6d2c"}, "trait": null, "encoded_token_ids": null}, "event_timestamp": 1726757612, "is_private_listing": false}, {"event_type": "order", "order_hash": "0x5f82bf80b2505901b450163006b37cc7260cfedf9d37b9773a1fc2a0bf07f085", "order_type": "listing", "chain": "base", "protocol_address": "0x0000000000000068f116a894984e2db1123eb395", "start_date": 1726757426, "expiration_date": 1726811426, "asset": {"identifier": "6773", "collection": "boredape-baseclub", "contract": "0x0be0bb1097f4465b17b1ac3b22b5427d9cbf6d2c", "token_standard": "erc721", "name": "BABC #6773", "description": "Discover the world of the Bored Ape Base Club (BABC) at boredapebaseclub.com , your exclusive gateway to a vibrant community on the Base Chain. Offering more than mere ownership, BABC NFTs act as a passport to an elite club for members only. By acquiring a BABC NFT, you gain access to private events and a chance to secure special edition Bitcoin NFTs. Join our community and explore the exclusive benefits awaiting BABC NFT holders.", "image_url": "https://ipfs.io/ipfs/bafybeign2he4am27blezmaiioylryyb2gtqd6jddbctxeyx7a2zmmo5dyu/6773", "display_image_url": "https://i.seadn.io/s/raw/files/b4483a52d0a85aa6b5e9abf5a842c0d1.png?w=500&auto=format", "display_animation_url": null, "metadata_url": "https://ipfs.io/ipfs/bafybeiacrqba67k6p7vu523mnumu36a34hcanowg4axxl2z3yse6ot437y/6773", "opensea_url": "https://opensea.io/assets/base/0x0be0bb1097f4465b17b1ac3b22b5427d9cbf6d2c/6773", "updated_at": "2024-10-06T22:40:44.777301", "is_disabled": false, "is_nsfw": false}, "quantity": 1, "maker": "0x1b5cbe0440861590ba929b2d0ef819a8f5f0d454", "taker": "", "payment": {"quantity": "1699999999000000", "token_address": "0x0000000000000000000000000000000000000000", "decimals": 18, "symbol": "ETH"}, "criteria": {}, "event_timestamp": 1726757427, "is_private_listing": false}, {"event_type": "order", "order_hash": "0x98a1bb8d7ec3461fa2bdf5a618d956b697cf8620bd915b3e6b225d471e401115", "order_type": "listing", "chain": "base", "protocol_address": "0x0000000000000068f116a894984e2db1123eb395", "start_date": 1726757393, "expiration_date": 1726811393, "asset": {"identifier": "2565", "collection": "boredape-baseclub", "contract": "0x0be0bb1097f4465b17b1ac3b22b5427d9cbf6d2c", "token_standard": "erc721", "name": "BABC #2565", "description": "Discover the world of the Bored Ape Base Club (BABC) at boredapebaseclub.com , your exclusive gateway to a vibrant community on the Base Chain. Offering more than mere ownership, BABC NFTs act as a passport to an elite club for members only. By acquiring a BABC NFT, you gain access to private events and a chance to secure special edition Bitcoin NFTs. Join our community and explore the exclusive benefits awaiting BABC NFT holders.", "image_url": "https://ipfs.io/ipfs/bafybeidkos7vbmer67i2d7dq67wtfmzd3dlgpujnx2cipse2dehe5xmu5a/2565", "display_image_url": "https://i.seadn.io/s/raw/files/30ee51cd880ee927b4b4d80facc17445.png?w=500&auto=format", "display_animation_url": null, "metadata_url": "https://ipfs.io/ipfs/bafybeiacrqba67k6p7vu523mnumu36a34hcanowg4axxl2z3yse6ot437y/2565", "opensea_url": "https://opensea.io/assets/base/0x0be0bb1097f4465b17b1ac3b22b5427d9cbf6d2c/2565", "updated_at": "2024-11-16T19:05:14.982676", "is_disabled": false, "is_nsfw": false}, "quantity": 1, "maker": "0x1b5cbe0440861590ba929b2d0ef819a8f5f0d454", "taker": "", "payment": {"quantity": "1699999999000000", "token_address": "0x0000000000000000000000000000000000000000", "decimals": 18, "symbol": "ETH"}, "criteria": {}, "event_timestamp": 1726757394, "is_private_listing": false}, {"event_type": "order", "order_hash": "0x9e6b1c0031cda127f8f3bb110c2f82316e29b5930a1ef3591123923148613884", "order_type": "listing", "chain": "base", "protocol_address": "0x0000000000000068f116a894984e2db1123eb395", "start_date": 1726757341, "expiration_date": 1726811341, "asset": {"identifier": "1585", "collection": "boredape-baseclub", "contract": "0x0be0bb1097f4465b17b1ac3b22b5427d9cbf6d2c", "token_standard": "erc721", "name": "BABC #1585", "description": "Discover the world of the Bored Ape Base Club (BABC) at boredapebaseclub.com , your exclusive gateway to a vibrant community on the Base Chain. Offering more than mere ownership, BABC NFTs act as a passport to an elite club for members only. By acquiring a BABC NFT, you gain access to private events and a chance to secure special edition Bitcoin NFTs. Join our community and explore the exclusive benefits awaiting BABC NFT holders.", "image_url": "https://ipfs.io/ipfs/bafybeihaue5tbwaisjlnkuneswhvv6qbmsimqgwee6xeejwc7hfenynwty/1585", "display_image_url": "https://i.seadn.io/s/raw/files/5f79b139d5b1cc7501ab461e24827216.png?w=500&auto=format", "display_animation_url": null, "metadata_url": "https://ipfs.io/ipfs/bafybeiacrqba67k6p7vu523mnumu36a34hcanowg4axxl2z3yse6ot437y/1585", "opensea_url": "https://opensea.io/assets/base/0x0be0bb1097f4465b17b1ac3b22b5427d9cbf6d2c/1585", "updated_at": "2024-10-06T22:41:54.437109", "is_disabled": false, "is_nsfw": false}, "quantity": 1, "maker": "0x1b5cbe0440861590ba929b2d0ef819a8f5f0d454", "taker": "", "payment": {"quantity": "1699999999000000", "token_address": "0x0000000000000000000000000000000000000000", "decimals": 18, "symbol": "ETH"}, "criteria": {}, "event_timestamp": 1726757343, "is_private_listing": false}, {"event_type": "order", "order_hash": "0x6ecbb8b1053eb489ff7e984fb4bb07ceca10da5634aa9273af60c05827c91525", "order_type": "listing", "chain": "base", "protocol_address": "0x0000000000000068f116a894984e2db1123eb395", "start_date": 1726757334, "expiration_date": 1726811334, "asset": {"identifier": "1488", "collection": "boredape-baseclub", "contract": "0x0be0bb1097f4465b17b1ac3b22b5427d9cbf6d2c", "token_standard": "erc721", "name": "BABC #1488", "description": "Discover the world of the Bored Ape Base Club (BABC) at boredapebaseclub.com , your exclusive gateway to a vibrant community on the Base Chain. Offering more than mere ownership, BABC NFTs act as a passport to an elite club for members only. By acquiring a BABC NFT, you gain access to private events and a chance to secure special edition Bitcoin NFTs. Join our community and explore the exclusive benefits awaiting BABC NFT holders.", "image_url": "https://ipfs.io/ipfs/bafybeihaue5tbwaisjlnkuneswhvv6qbmsimqgwee6xeejwc7hfenynwty/1488", "display_image_url": "https://i.seadn.io/s/raw/files/53b3773c48b6e3cc6331e89be8088809.png?w=500&auto=format", "display_animation_url": null, "metadata_url": "https://ipfs.io/ipfs/bafybeiacrqba67k6p7vu523mnumu36a34hcanowg4axxl2z3yse6ot437y/1488", "opensea_url": "https://opensea.io/assets/base/0x0be0bb1097f4465b17b1ac3b22b5427d9cbf6d2c/1488", "updated_at": "2024-10-23T10:38:42.475635", "is_disabled": false, "is_nsfw": false}, "quantity": 1, "maker": "0x1b5cbe0440861590ba929b2d0ef819a8f5f0d454", "taker": "", "payment": {"quantity": "1699999999000000", "token_address": "0x0000000000000000000000000000000000000000", "decimals": 18, "symbol": "ETH"}, "criteria": {}, "event_timestamp": 1726757336, "is_private_listing": false}, {"event_type": "order", "order_hash": "0xbd561e97caf139ee1f3682dadd06f6c53992c83923f7571f5f706302e24b58e3", "order_type": "collection_offer", "chain": "base", "protocol_address": "0x0000000000000068f116a894984e2db1123eb395", "start_date": 1726756836, "expiration_date": 1726758336, "asset": null, "quantity": 2, "maker": "0xd4f4f6a1f386e041984da38e7be351903c767c2d", "taker": "", "payment": {"quantity": "1000000000000000", "token_address": "0x4200000000000000000000000000000000000006", "decimals": 18, "symbol": "WETH"}, "criteria": {"collection": {"slug": "boredape-baseclub"}, "contract": {"address": "0x0be0bb1097f4465b17b1ac3b22b5427d9cbf6d2c"}, "trait": null, "encoded_token_ids": null}, "event_timestamp": 1726756838, "is_private_listing": false}, {"event_type": "order", "order_hash": "0x08d60d4d9ecc2e3837061ca8a102d82f0dba54acdc588cb2b3dcede821cc3b8f", "order_type": "collection_offer", "chain": "base", "protocol_address": "0x0000000000000068f116a894984e2db1123eb395", "start_date": 1726756832, "expiration_date": 1726758332, "asset": null, "quantity": 4, "maker": "0xd4f4f6a1f386e041984da38e7be351903c767c2d", "taker": "", "payment": {"quantity": "1600000000000000", "token_address": "0x4200000000000000000000000000000000000006", "decimals": 18, "symbol": "WETH"}, "criteria": {"collection": {"slug": "boredape-baseclub"}, "contract": {"address": "0x0be0bb1097f4465b17b1ac3b22b5427d9cbf6d2c"}, "trait": null, "encoded_token_ids": null}, "event_timestamp": 1726756834, "is_private_listing": false}, {"event_type": "order", "order_hash": "0xf43ead42cf3d05dd9d245321cb7926972a6125671f60d998213b61e8d78cf929", "order_type": "collection_offer", "chain": "base", "protocol_address": "0x0000000000000068f116a894984e2db1123eb395", "start_date": 1726756829, "expiration_date": 1726758329, "asset": null, "quantity": 6, "maker": "0xd4f4f6a1f386e041984da38e7be351903c767c2d", "taker": "", "payment": {"quantity": "1200000000000000", "token_address": "0x4200000000000000000000000000000000000006", "decimals": 18, "symbol": "WETH"}, "criteria": {"collection": {"slug": "boredape-baseclub"}, "contract": {"address": "0x0be0bb1097f4465b17b1ac3b22b5427d9cbf6d2c"}, "trait": null, "encoded_token_ids": null}, "event_timestamp": 1726756831, "is_private_listing": false}, {"event_type": "order", "order_hash": "0xd91d8269c887da984d084375f7a47b0195981368be4de5435c0339484d3153ec", "order_type": "collection_offer", "chain": "base", "protocol_address": "0x0000000000000068f116a894984e2db1123eb395", "start_date": 1726756074, "expiration_date": 1726757574, "asset": null, "quantity": 2, "maker": "0xd4f4f6a1f386e041984da38e7be351903c767c2d", "taker": "", "payment": {"quantity": "1000000000000000", "token_address": "0x4200000000000000000000000000000000000006", "decimals": 18, "symbol": "WETH"}, "criteria": {"collection": {"slug": "boredape-baseclub"}, "contract": {"address": "0x0be0bb1097f4465b17b1ac3b22b5427d9cbf6d2c"}, "trait": null, "encoded_token_ids": null}, "event_timestamp": 1726756076, "is_private_listing": false}, {"event_type": "order", "order_hash": "0x81f6b0977877f558d146683097f3565044ab4cf571858d756f074157db83cc41", "order_type": "collection_offer", "chain": "base", "protocol_address": "0x0000000000000068f116a894984e2db1123eb395", "start_date": 1726756071, "expiration_date": 1726757571, "asset": null, "quantity": 4, "maker": "0xd4f4f6a1f386e041984da38e7be351903c767c2d", "taker": "", "payment": {"quantity": "1600000000000000", "token_address": "0x4200000000000000000000000000000000000006", "decimals": 18, "symbol": "WETH"}, "criteria": {"collection": {"slug": "boredape-baseclub"}, "contract": {"address": "0x0be0bb1097f4465b17b1ac3b22b5427d9cbf6d2c"}, "trait": null, "encoded_token_ids": null}, "event_timestamp": 1726756073, "is_private_listing": false}, {"event_type": "order", "order_hash": "0xc644c82dc672adbe3366be29aec8c378c1d6217510da13be469e41f0fcd740b0", "order_type": "collection_offer", "chain": "base", "protocol_address": "0x0000000000000068f116a894984e2db1123eb395", "start_date": 1726756068, "expiration_date": 1726757568, "asset": null, "quantity": 6, "maker": "0xd4f4f6a1f386e041984da38e7be351903c767c2d", "taker": "", "payment": {"quantity": "1200000000000000", "token_address": "0x4200000000000000000000000000000000000006", "decimals": 18, "symbol": "WETH"}, "criteria": {"collection": {"slug": "boredape-baseclub"}, "contract": {"address": "0x0be0bb1097f4465b17b1ac3b22b5427d9cbf6d2c"}, "trait": null, "encoded_token_ids": null}, "event_timestamp": 1726756070, "is_private_listing": false}, {"event_type": "order", "order_hash": "0x91a2ec1ba440eb1005f1c2469742de7774d2d8f57d86ded6b9759fcd788fca4d", "order_type": "collection_offer", "chain": "base", "protocol_address": "0x0000000000000068f116a894984e2db1123eb395", "start_date": 1726755288, "expiration_date": 1726756788, "asset": null, "quantity": 2, "maker": "0xd4f4f6a1f386e041984da38e7be351903c767c2d", "taker": "", "payment": {"quantity": "1000000000000000", "token_address": "0x4200000000000000000000000000000000000006", "decimals": 18, "symbol": "WETH"}, "criteria": {"collection": {"slug": "boredape-baseclub"}, "contract": {"address": "0x0be0bb1097f4465b17b1ac3b22b5427d9cbf6d2c"}, "trait": null, "encoded_token_ids": null}, "event_timestamp": 1726755297, "is_private_listing": false}, {"event_type": "order", "order_hash": "0xf14be72265e183bb92bab3eda4e02bc8f29e7ee5256482fe7becb107a5c70434", "order_type": "collection_offer", "chain": "base", "protocol_address": "0x0000000000000068f116a894984e2db1123eb395", "start_date": 1726755285, "expiration_date": 1726756785, "asset": null, "quantity": 4, "maker": "0xd4f4f6a1f386e041984da38e7be351903c767c2d", "taker": "", "payment": {"quantity": "1600000000000000", "token_address": "0x4200000000000000000000000000000000000006", "decimals": 18, "symbol": "WETH"}, "criteria": {"collection": {"slug": "boredape-baseclub"}, "contract": {"address": "0x0be0bb1097f4465b17b1ac3b22b5427d9cbf6d2c"}, "trait": null, "encoded_token_ids": null}, "event_timestamp": 1726755287, "is_private_listing": false}, {"event_type": "order", "order_hash": "0x893ddabb5bab6c6fa5fe747fe2cad5fcfe1323bc0f3a859fcf3dd3f15cbfafd3", "order_type": "collection_offer", "chain": "base", "protocol_address": "0x0000000000000068f116a894984e2db1123eb395", "start_date": 1726755281, "expiration_date": 1726756781, "asset": null, "quantity": 6, "maker": "0xd4f4f6a1f386e041984da38e7be351903c767c2d", "taker": "", "payment": {"quantity": "1200000000000000", "token_address": "0x4200000000000000000000000000000000000006", "decimals": 18, "symbol": "WETH"}, "criteria": {"collection": {"slug": "boredape-baseclub"}, "contract": {"address": "0x0be0bb1097f4465b17b1ac3b22b5427d9cbf6d2c"}, "trait": null, "encoded_token_ids": null}, "event_timestamp": 1726755283, "is_private_listing": false}, {"event_type": "order", "order_hash": "0x3a11983e528724eb6a27f035e3ce578727c60ccfbd335de45a3db3576ba029e6", "order_type": "listing", "chain": "base", "protocol_address": "0x0000000000000068f116a894984e2db1123eb395", "start_date": 1726754539, "expiration_date": 1727013739, "asset": {"identifier": "2023", "collection": "boredape-baseclub", "contract": "0x0be0bb1097f4465b17b1ac3b22b5427d9cbf6d2c", "token_standard": "erc721", "name": "BABC #2023", "description": "Discover the world of the Bored Ape Base Club (BABC) at boredapebaseclub.com , your exclusive gateway to a vibrant community on the Base Chain. Offering more than mere ownership, BABC NFTs act as a passport to an elite club for members only. By acquiring a BABC NFT, you gain access to private events and a chance to secure special edition Bitcoin NFTs. Join our community and explore the exclusive benefits awaiting BABC NFT holders.", "image_url": "https://ipfs.io/ipfs/bafybeie3ah6zeyvuqcj7z55ca6xfyl5anzcjsaobkyc637j56g4qioqtwa/2023", "display_image_url": "https://i.seadn.io/s/raw/files/654bd9c9e74804df72402c0893b53656.png?w=500&auto=format", "display_animation_url": null, "metadata_url": "https://ipfs.io/ipfs/bafybeiacrqba67k6p7vu523mnumu36a34hcanowg4axxl2z3yse6ot437y/2023", "opensea_url": "https://opensea.io/assets/base/0x0be0bb1097f4465b17b1ac3b22b5427d9cbf6d2c/2023", "updated_at": "2024-12-14T15:04:54.026839", "is_disabled": false, "is_nsfw": false}, "quantity": 1, "maker": "0xd4f4f6a1f386e041984da38e7be351903c767c2d", "taker": "", "payment": {"quantity": "6600000000000000", "token_address": "0x0000000000000000000000000000000000000000", "decimals": 18, "symbol": "ETH"}, "criteria": {}, "event_timestamp": 1726754541, "is_private_listing": false}, {"event_type": "order", "order_hash": "0x2b099e989f5b85c804014946c0a1c64c9de888d0827863f3665625cdc45c0690", "order_type": "listing", "chain": "base", "protocol_address": "0x0000000000000068f116a894984e2db1123eb395", "start_date": 1726754533, "expiration_date": 1727013733, "asset": {"identifier": "2073", "collection": "boredape-baseclub", "contract": "0x0be0bb1097f4465b17b1ac3b22b5427d9cbf6d2c", "token_standard": "erc721", "name": "BABC #2073", "description": "Discover the world of the Bored Ape Base Club (BABC) at boredapebaseclub.com , your exclusive gateway to a vibrant community on the Base Chain. Offering more than mere ownership, BABC NFTs act as a passport to an elite club for members only. By acquiring a BABC NFT, you gain access to private events and a chance to secure special edition Bitcoin NFTs. Join our community and explore the exclusive benefits awaiting BABC NFT holders.", "image_url": "https://ipfs.io/ipfs/bafybeie3ah6zeyvuqcj7z55ca6xfyl5anzcjsaobkyc637j56g4qioqtwa/2073", "display_image_url": "https://i.seadn.io/s/raw/files/4595f908fa243aab8067c644a85ed671.png?w=500&auto=format", "display_animation_url": null, "metadata_url": "https://ipfs.io/ipfs/bafybeiacrqba67k6p7vu523mnumu36a34hcanowg4axxl2z3yse6ot437y/2073", "opensea_url": "https://opensea.io/assets/base/0x0be0bb1097f4465b17b1ac3b22b5427d9cbf6d2c/2073", "updated_at": "2024-12-06T19:39:57.602658", "is_disabled": false, "is_nsfw": false}, "quantity": 1, "maker": "0xd4f4f6a1f386e041984da38e7be351903c767c2d", "taker": "", "payment": {"quantity": "6600000000000000", "token_address": "0x0000000000000000000000000000000000000000", "decimals": 18, "symbol": "ETH"}, "criteria": {}, "event_timestamp": 1726754535, "is_private_listing": false}, {"event_type": "order", "order_hash": "0x7f91241f05400bb858635072955808f0139b88726ca084424d3f68bd270e293e", "order_type": "collection_offer", "chain": "base", "protocol_address": "0x0000000000000068f116a894984e2db1123eb395", "start_date": 1726754532, "expiration_date": 1726756032, "asset": null, "quantity": 2, "maker": "0xd4f4f6a1f386e041984da38e7be351903c767c2d", "taker": "", "payment": {"quantity": "1000000000000000", "token_address": "0x4200000000000000000000000000000000000006", "decimals": 18, "symbol": "WETH"}, "criteria": {"collection": {"slug": "boredape-baseclub"}, "contract": {"address": "0x0be0bb1097f4465b17b1ac3b22b5427d9cbf6d2c"}, "trait": null, "encoded_token_ids": null}, "event_timestamp": 1726754534, "is_private_listing": false}, {"event_type": "order", "order_hash": "0x0c81d73bf4ff2161acd45a03121beef78003c5194fc2553bdb755449a0c3a439", "order_type": "collection_offer", "chain": "base", "protocol_address": "0x0000000000000068f116a894984e2db1123eb395", "start_date": 1726754529, "expiration_date": 1726756028, "asset": null, "quantity": 4, "maker": "0xd4f4f6a1f386e041984da38e7be351903c767c2d", "taker": "", "payment": {"quantity": "1600000000000000", "token_address": "0x4200000000000000000000000000000000000006", "decimals": 18, "symbol": "WETH"}, "criteria": {"collection": {"slug": "boredape-baseclub"}, "contract": {"address": "0x0be0bb1097f4465b17b1ac3b22b5427d9cbf6d2c"}, "trait": null, "encoded_token_ids": null}, "event_timestamp": 1726754531, "is_private_listing": false}, {"event_type": "order", "order_hash": "0x7cd8d120110ef03c736c87d549b67d674ecf366fe92f30ed73a28c8d092ca8a5", "order_type": "collection_offer", "chain": "base", "protocol_address": "0x0000000000000068f116a894984e2db1123eb395", "start_date": 1726754525, "expiration_date": 1726756025, "asset": null, "quantity": 6, "maker": "0xd4f4f6a1f386e041984da38e7be351903c767c2d", "taker": "", "payment": {"quantity": "1200000000000000", "token_address": "0x4200000000000000000000000000000000000006", "decimals": 18, "symbol": "WETH"}, "criteria": {"collection": {"slug": "boredape-baseclub"}, "contract": {"address": "0x0be0bb1097f4465b17b1ac3b22b5427d9cbf6d2c"}, "trait": null, "encoded_token_ids": null}, "event_timestamp": 1726754527, "is_private_listing": false}, {"event_type": "order", "order_hash": "0xc4a4f29eed01c9b548ed81a1dd33b50add413fa44f6c3dbd797cced17f8d1a6e", "order_type": "collection_offer", "chain": "base", "protocol_address": "0x0000000000000068f116a894984e2db1123eb395", "start_date": 1726753738, "expiration_date": 1726755237, "asset": null, "quantity": 2, "maker": "0xd4f4f6a1f386e041984da38e7be351903c767c2d", "taker": "", "payment": {"quantity": "1000000000000000", "token_address": "0x4200000000000000000000000000000000000006", "decimals": 18, "symbol": "WETH"}, "criteria": {"collection": {"slug": "boredape-baseclub"}, "contract": {"address": "0x0be0bb1097f4465b17b1ac3b22b5427d9cbf6d2c"}, "trait": null, "encoded_token_ids": null}, "event_timestamp": 1726753740, "is_private_listing": false}, {"event_type": "order", "order_hash": "0x215d33203f3262d00552bfdfd2eb661cc2c6d8d14a900d4d8b9c993606a7a9fb", "order_type": "collection_offer", "chain": "base", "protocol_address": "0x0000000000000068f116a894984e2db1123eb395", "start_date": 1726753734, "expiration_date": 1726755234, "asset": null, "quantity": 4, "maker": "0xd4f4f6a1f386e041984da38e7be351903c767c2d", "taker": "", "payment": {"quantity": "1600000000000000", "token_address": "0x4200000000000000000000000000000000000006", "decimals": 18, "symbol": "WETH"}, "criteria": {"collection": {"slug": "boredape-baseclub"}, "contract": {"address": "0x0be0bb1097f4465b17b1ac3b22b5427d9cbf6d2c"}, "trait": null, "encoded_token_ids": null}, "event_timestamp": 1726753736, "is_private_listing": false}, {"event_type": "order", "order_hash": "0xc9f486ebd770ece9ebef356359e6881f4e039dc60961900ae928ea02647b0b92", "order_type": "collection_offer", "chain": "base", "protocol_address": "0x0000000000000068f116a894984e2db1123eb395", "start_date": 1726753731, "expiration_date": 1726755231, "asset": null, "quantity": 6, "maker": "0xd4f4f6a1f386e041984da38e7be351903c767c2d", "taker": "", "payment": {"quantity": "1200000000000000", "token_address": "0x4200000000000000000000000000000000000006", "decimals": 18, "symbol": "WETH"}, "criteria": {"collection": {"slug": "boredape-baseclub"}, "contract": {"address": "0x0be0bb1097f4465b17b1ac3b22b5427d9cbf6d2c"}, "trait": null, "encoded_token_ids": null}, "event_timestamp": 1726753733, "is_private_listing": false}, {"event_type": "order", "order_hash": "0xf1e557e24b2a179d7246a52b2dcee7674c952e3f6ac2671bedf19e33fe5f8bd1", "order_type": "collection_offer", "chain": "base", "protocol_address": "0x0000000000000068f116a894984e2db1123eb395", "start_date": 1726752976, "expiration_date": 1726754476, "asset": null, "quantity": 2, "maker": "0xd4f4f6a1f386e041984da38e7be351903c767c2d", "taker": "", "payment": {"quantity": "1000000000000000", "token_address": "0x4200000000000000000000000000000000000006", "decimals": 18, "symbol": "WETH"}, "criteria": {"collection": {"slug": "boredape-baseclub"}, "contract": {"address": "0x0be0bb1097f4465b17b1ac3b22b5427d9cbf6d2c"}, "trait": null, "encoded_token_ids": null}, "event_timestamp": 1726752978, "is_private_listing": false}, {"event_type": "order", "order_hash": "0xef190a2dadd4701234939bed03bf90c29e8934073d789cc395bb857d9ed75555", "order_type": "collection_offer", "chain": "base", "protocol_address": "0x0000000000000068f116a894984e2db1123eb395", "start_date": 1726752973, "expiration_date": 1726754473, "asset": null, "quantity": 4, "maker": "0xd4f4f6a1f386e041984da38e7be351903c767c2d", "taker": "", "payment": {"quantity": "1600000000000000", "token_address": "0x4200000000000000000000000000000000000006", "decimals": 18, "symbol": "WETH"}, "criteria": {"collection": {"slug": "boredape-baseclub"}, "contract": {"address": "0x0be0bb1097f4465b17b1ac3b22b5427d9cbf6d2c"}, "trait": null, "encoded_token_ids": null}, "event_timestamp": 1726752975, "is_private_listing": false}, {"event_type": "order", "order_hash": "0xe4c7c1524a5c19bf190508651f87ef2604cf736a1eee81c9c7fdd530e2ec014b", "order_type": "collection_offer", "chain": "base", "protocol_address": "0x0000000000000068f116a894984e2db1123eb395", "start_date": 1726752970, "expiration_date": 1726754470, "asset": null, "quantity": 6, "maker": "0xd4f4f6a1f386e041984da38e7be351903c767c2d", "taker": "", "payment": {"quantity": "1200000000000000", "token_address": "0x4200000000000000000000000000000000000006", "decimals": 18, "symbol": "WETH"}, "criteria": {"collection": {"slug": "boredape-baseclub"}, "contract": {"address": "0x0be0bb1097f4465b17b1ac3b22b5427d9cbf6d2c"}, "trait": null, "encoded_token_ids": null}, "event_timestamp": 1726752972, "is_private_listing": false}, {"event_type": "order", "order_hash": "0x611e6974be1e7449f0c7ebc52ae2bafaa1e909d5ef921b88028a270b3bd5a09b", "order_type": "collection_offer", "chain": "base", "protocol_address": "0x0000000000000068f116a894984e2db1123eb395", "start_date": 1726752203, "expiration_date": 1726753703, "asset": null, "quantity": 2, "maker": "0xd4f4f6a1f386e041984da38e7be351903c767c2d", "taker": "", "payment": {"quantity": "1000000000000000", "token_address": "0x4200000000000000000000000000000000000006", "decimals": 18, "symbol": "WETH"}, "criteria": {"collection": {"slug": "boredape-baseclub"}, "contract": {"address": "0x0be0bb1097f4465b17b1ac3b22b5427d9cbf6d2c"}, "trait": null, "encoded_token_ids": null}, "event_timestamp": 1726752205, "is_private_listing": false}, {"event_type": "order", "order_hash": "0x3d48824d4637b3932c45f601a2ad254180dfa0aead9d6222d4ea5729547216a8", "order_type": "collection_offer", "chain": "base", "protocol_address": "0x0000000000000068f116a894984e2db1123eb395", "start_date": 1726752200, "expiration_date": 1726753700, "asset": null, "quantity": 4, "maker": "0xd4f4f6a1f386e041984da38e7be351903c767c2d", "taker": "", "payment": {"quantity": "1600000000000000", "token_address": "0x4200000000000000000000000000000000000006", "decimals": 18, "symbol": "WETH"}, "criteria": {"collection": {"slug": "boredape-baseclub"}, "contract": {"address": "0x0be0bb1097f4465b17b1ac3b22b5427d9cbf6d2c"}, "trait": null, "encoded_token_ids": null}, "event_timestamp": 1726752202, "is_private_listing": false}, {"event_type": "order", "order_hash": "0x385ab8845c6d36a82481b08c569bd2a03bb8cabfbade1520140e256d8aed39b2", "order_type": "collection_offer", "chain": "base", "protocol_address": "0x0000000000000068f116a894984e2db1123eb395", "start_date": 1726752197, "expiration_date": 1726753697, "asset": null, "quantity": 6, "maker": "0xd4f4f6a1f386e041984da38e7be351903c767c2d", "taker": "", "payment": {"quantity": "1200000000000000", "token_address": "0x4200000000000000000000000000000000000006", "decimals": 18, "symbol": "WETH"}, "criteria": {"collection": {"slug": "boredape-baseclub"}, "contract": {"address": "0x0be0bb1097f4465b17b1ac3b22b5427d9cbf6d2c"}, "trait": null, "encoded_token_ids": null}, "event_timestamp": 1726752199, "is_private_listing": false}, {"event_type": "order", "order_hash": "0x2f806a73d1284bf5731a47a56dadc32dde56db4552088d88cc9c42f14ac5a2cc", "order_type": "collection_offer", "chain": "base", "protocol_address": "0x0000000000000068f116a894984e2db1123eb395", "start_date": 1726751415, "expiration_date": 1726752915, "asset": null, "quantity": 2, "maker": "0xd4f4f6a1f386e041984da38e7be351903c767c2d", "taker": "", "payment": {"quantity": "1000000000000000", "token_address": "0x4200000000000000000000000000000000000006", "decimals": 18, "symbol": "WETH"}, "criteria": {"collection": {"slug": "boredape-baseclub"}, "contract": {"address": "0x0be0bb1097f4465b17b1ac3b22b5427d9cbf6d2c"}, "trait": null, "encoded_token_ids": null}, "event_timestamp": 1726751417, "is_private_listing": false}, {"event_type": "order", "order_hash": "0xe13f0b397cabc69b81e5c90a64411839430c82dd742b42affaef9f3588186664", "order_type": "collection_offer", "chain": "base", "protocol_address": "0x0000000000000068f116a894984e2db1123eb395", "start_date": 1726751411, "expiration_date": 1726752911, "asset": null, "quantity": 4, "maker": "0xd4f4f6a1f386e041984da38e7be351903c767c2d", "taker": "", "payment": {"quantity": "1600000000000000", "token_address": "0x4200000000000000000000000000000000000006", "decimals": 18, "symbol": "WETH"}, "criteria": {"collection": {"slug": "boredape-baseclub"}, "contract": {"address": "0x0be0bb1097f4465b17b1ac3b22b5427d9cbf6d2c"}, "trait": null, "encoded_token_ids": null}, "event_timestamp": 1726751413, "is_private_listing": false}, {"event_type": "order", "order_hash": "0xb2b8ead90d93b302c4597c2b135bc82820b53b079611fb2f12dc3b37d9170aac", "order_type": "collection_offer", "chain": "base", "protocol_address": "0x0000000000000068f116a894984e2db1123eb395", "start_date": 1726751408, "expiration_date": 1726752908, "asset": null, "quantity": 6, "maker": "0xd4f4f6a1f386e041984da38e7be351903c767c2d", "taker": "", "payment": {"quantity": "1200000000000000", "token_address": "0x4200000000000000000000000000000000000006", "decimals": 18, "symbol": "WETH"}, "criteria": {"collection": {"slug": "boredape-baseclub"}, "contract": {"address": "0x0be0bb1097f4465b17b1ac3b22b5427d9cbf6d2c"}, "trait": null, "encoded_token_ids": null}, "event_timestamp": 1726751410, "is_private_listing": false}, {"event_type": "order", "order_hash": "0x6b8272691ecce352e5fad5d034f0eac5094363f2af9e567cce451d300c8aedd9", "order_type": "collection_offer", "chain": "base", "protocol_address": "0x0000000000000068f116a894984e2db1123eb395", "start_date": 1726750628, "expiration_date": 1726752128, "asset": null, "quantity": 2, "maker": "0xd4f4f6a1f386e041984da38e7be351903c767c2d", "taker": "", "payment": {"quantity": "1000000000000000", "token_address": "0x4200000000000000000000000000000000000006", "decimals": 18, "symbol": "WETH"}, "criteria": {"collection": {"slug": "boredape-baseclub"}, "contract": {"address": "0x0be0bb1097f4465b17b1ac3b22b5427d9cbf6d2c"}, "trait": null, "encoded_token_ids": null}, "event_timestamp": 1726750630, "is_private_listing": false}, {"event_type": "order", "order_hash": "0x38edfa2148eee1ec3f7152bc34a1171018a78736d180ca966df4cf7b42c2ae9d", "order_type": "collection_offer", "chain": "base", "protocol_address": "0x0000000000000068f116a894984e2db1123eb395", "start_date": 1726750625, "expiration_date": 1726752125, "asset": null, "quantity": 4, "maker": "0xd4f4f6a1f386e041984da38e7be351903c767c2d", "taker": "", "payment": {"quantity": "1600000000000000", "token_address": "0x4200000000000000000000000000000000000006", "decimals": 18, "symbol": "WETH"}, "criteria": {"collection": {"slug": "boredape-baseclub"}, "contract": {"address": "0x0be0bb1097f4465b17b1ac3b22b5427d9cbf6d2c"}, "trait": null, "encoded_token_ids": null}, "event_timestamp": 1726750627, "is_private_listing": false}, {"event_type": "order", "order_hash": "0xbcfd8904b49c7e3f8a98b74038f8702f4b318cd5612993dfa2d8ad8d9aa7a5a2", "order_type": "collection_offer", "chain": "base", "protocol_address": "0x0000000000000068f116a894984e2db1123eb395", "start_date": 1726750622, "expiration_date": 1726752121, "asset": null, "quantity": 6, "maker": "0xd4f4f6a1f386e041984da38e7be351903c767c2d", "taker": "", "payment": {"quantity": "1200000000000000", "token_address": "0x4200000000000000000000000000000000000006", "decimals": 18, "symbol": "WETH"}, "criteria": {"collection": {"slug": "boredape-baseclub"}, "contract": {"address": "0x0be0bb1097f4465b17b1ac3b22b5427d9cbf6d2c"}, "trait": null, "encoded_token_ids": null}, "event_timestamp": 1726750624, "is_private_listing": false}, {"event_type": "order", "order_hash": "0xfd0e9f54ad67212b286ccf676514ae8401e48a3d6e73c0e145d6d4994008dd75", "order_type": "collection_offer", "chain": "base", "protocol_address": "0x0000000000000068f116a894984e2db1123eb395", "start_date": 1726749873, "expiration_date": 1726751373, "asset": null, "quantity": 2, "maker": "0xd4f4f6a1f386e041984da38e7be351903c767c2d", "taker": "", "payment": {"quantity": "1000000000000000", "token_address": "0x4200000000000000000000000000000000000006", "decimals": 18, "symbol": "WETH"}, "criteria": {"collection": {"slug": "boredape-baseclub"}, "contract": {"address": "0x0be0bb1097f4465b17b1ac3b22b5427d9cbf6d2c"}, "trait": null, "encoded_token_ids": null}, "event_timestamp": 1726749875, "is_private_listing": false}, {"event_type": "order", "order_hash": "0x8031354eac98621225928b6bd7032aa0b0e03b8048dae1822685e58be1631bb6", "order_type": "collection_offer", "chain": "base", "protocol_address": "0x0000000000000068f116a894984e2db1123eb395", "start_date": 1726749870, "expiration_date": 1726751370, "asset": null, "quantity": 4, "maker": "0xd4f4f6a1f386e041984da38e7be351903c767c2d", "taker": "", "payment": {"quantity": "1600000000000000", "token_address": "0x4200000000000000000000000000000000000006", "decimals": 18, "symbol": "WETH"}, "criteria": {"collection": {"slug": "boredape-baseclub"}, "contract": {"address": "0x0be0bb1097f4465b17b1ac3b22b5427d9cbf6d2c"}, "trait": null, "encoded_token_ids": null}, "event_timestamp": 1726749872, "is_private_listing": false}, {"event_type": "order", "order_hash": "0x856431fd1095b4aeedfceaa884807e4d03bed4cd67b8af5683eef2a85781bda8", "order_type": "collection_offer", "chain": "base", "protocol_address": "0x0000000000000068f116a894984e2db1123eb395", "start_date": 1726749867, "expiration_date": 1726751367, "asset": null, "quantity": 6, "maker": "0xd4f4f6a1f386e041984da38e7be351903c767c2d", "taker": "", "payment": {"quantity": "1200000000000000", "token_address": "0x4200000000000000000000000000000000000006", "decimals": 18, "symbol": "WETH"}, "criteria": {"collection": {"slug": "boredape-baseclub"}, "contract": {"address": "0x0be0bb1097f4465b17b1ac3b22b5427d9cbf6d2c"}, "trait": null, "encoded_token_ids": null}, "event_timestamp": 1726749869, "is_private_listing": false}, {"event_type": "order", "order_hash": "0x30876781f3f9ae3ef0cc9b4031d61ede7d8cb41cf8f55cf0f71997ab5a1a71ac", "order_type": "collection_offer", "chain": "base", "protocol_address": "0x0000000000000068f116a894984e2db1123eb395", "start_date": 1726749110, "expiration_date": 1726750610, "asset": null, "quantity": 2, "maker": "0xd4f4f6a1f386e041984da38e7be351903c767c2d", "taker": "", "payment": {"quantity": "1000000000000000", "token_address": "0x4200000000000000000000000000000000000006", "decimals": 18, "symbol": "WETH"}, "criteria": {"collection": {"slug": "boredape-baseclub"}, "contract": {"address": "0x0be0bb1097f4465b17b1ac3b22b5427d9cbf6d2c"}, "trait": null, "encoded_token_ids": null}, "event_timestamp": 1726749112, "is_private_listing": false}, {"event_type": "order", "order_hash": "0xe3fa784bbf85528ac6135f2a206ce1cda20f068e4b6caf2fffad301439af18ec", "order_type": "collection_offer", "chain": "base", "protocol_address": "0x0000000000000068f116a894984e2db1123eb395", "start_date": 1726749107, "expiration_date": 1726750606, "asset": null, "quantity": 4, "maker": "0xd4f4f6a1f386e041984da38e7be351903c767c2d", "taker": "", "payment": {"quantity": "1600000000000000", "token_address": "0x4200000000000000000000000000000000000006", "decimals": 18, "symbol": "WETH"}, "criteria": {"collection": {"slug": "boredape-baseclub"}, "contract": {"address": "0x0be0bb1097f4465b17b1ac3b22b5427d9cbf6d2c"}, "trait": null, "encoded_token_ids": null}, "event_timestamp": 1726749109, "is_private_listing": false}, {"event_type": "order", "order_hash": "0xd15d157c3c8629b4b15647595243612e622845c5d6971120032aeec9f5a1d44e", "order_type": "collection_offer", "chain": "base", "protocol_address": "0x0000000000000068f116a894984e2db1123eb395", "start_date": 1726749103, "expiration_date": 1726750603, "asset": null, "quantity": 6, "maker": "0xd4f4f6a1f386e041984da38e7be351903c767c2d", "taker": "", "payment": {"quantity": "1200000000000000", "token_address": "0x4200000000000000000000000000000000000006", "decimals": 18, "symbol": "WETH"}, "criteria": {"collection": {"slug": "boredape-baseclub"}, "contract": {"address": "0x0be0bb1097f4465b17b1ac3b22b5427d9cbf6d2c"}, "trait": null, "encoded_token_ids": null}, "event_timestamp": 1726749105, "is_private_listing": false}, {"event_type": "order", "order_hash": "0x857e89b676574a0a3696964f2c293186a7abe6dd984d9f7fcb3e8f9ff4704ae4", "order_type": "collection_offer", "chain": "base", "protocol_address": "0x0000000000000068f116a894984e2db1123eb395", "start_date": 1726748361, "expiration_date": 1726749861, "asset": null, "quantity": 2, "maker": "0xd4f4f6a1f386e041984da38e7be351903c767c2d", "taker": "", "payment": {"quantity": "1000000000000000", "token_address": "0x4200000000000000000000000000000000000006", "decimals": 18, "symbol": "WETH"}, "criteria": {"collection": {"slug": "boredape-baseclub"}, "contract": {"address": "0x0be0bb1097f4465b17b1ac3b22b5427d9cbf6d2c"}, "trait": null, "encoded_token_ids": null}, "event_timestamp": 1726748363, "is_private_listing": false}, {"event_type": "order", "order_hash": "0x705b036155da9c6f66d627560dcf834d0c12a0acf1e768b4490bfce785ba594e", "order_type": "collection_offer", "chain": "base", "protocol_address": "0x0000000000000068f116a894984e2db1123eb395", "start_date": 1726748358, "expiration_date": 1726749858, "asset": null, "quantity": 4, "maker": "0xd4f4f6a1f386e041984da38e7be351903c767c2d", "taker": "", "payment": {"quantity": "1600000000000000", "token_address": "0x4200000000000000000000000000000000000006", "decimals": 18, "symbol": "WETH"}, "criteria": {"collection": {"slug": "boredape-baseclub"}, "contract": {"address": "0x0be0bb1097f4465b17b1ac3b22b5427d9cbf6d2c"}, "trait": null, "encoded_token_ids": null}, "event_timestamp": 1726748360, "is_private_listing": false}, {"event_type": "order", "order_hash": "0xcb04cd86997224d5e5bd438d4d2abd5269c4819beea28ff2a4eb12d5ab8161ca", "order_type": "collection_offer", "chain": "base", "protocol_address": "0x0000000000000068f116a894984e2db1123eb395", "start_date": 1726748354, "expiration_date": 1726749854, "asset": null, "quantity": 6, "maker": "0xd4f4f6a1f386e041984da38e7be351903c767c2d", "taker": "", "payment": {"quantity": "1200000000000000", "token_address": "0x4200000000000000000000000000000000000006", "decimals": 18, "symbol": "WETH"}, "criteria": {"collection": {"slug": "boredape-baseclub"}, "contract": {"address": "0x0be0bb1097f4465b17b1ac3b22b5427d9cbf6d2c"}, "trait": null, "encoded_token_ids": null}, "event_timestamp": 1726748356, "is_private_listing": false}, {"event_type": "order", "order_hash": "0x6d19a741667a6f21393d7383a01467cc3b947fe005398149186cf3caf91adb01", "order_type": "collection_offer", "chain": "base", "protocol_address": "0x0000000000000068f116a894984e2db1123eb395", "start_date": 1726747616, "expiration_date": 1726749116, "asset": null, "quantity": 2, "maker": "0xd4f4f6a1f386e041984da38e7be351903c767c2d", "taker": "", "payment": {"quantity": "1000000000000000", "token_address": "0x4200000000000000000000000000000000000006", "decimals": 18, "symbol": "WETH"}, "criteria": {"collection": {"slug": "boredape-baseclub"}, "contract": {"address": "0x0be0bb1097f4465b17b1ac3b22b5427d9cbf6d2c"}, "trait": null, "encoded_token_ids": null}, "event_timestamp": 1726747618, "is_private_listing": false}, {"event_type": "order", "order_hash": "0x9b578213070e5d8442bd660ed6bf25b143e2e90beb9a531797048d238806a975", "order_type": "collection_offer", "chain": "base", "protocol_address": "0x0000000000000068f116a894984e2db1123eb395", "start_date": 1726747613, "expiration_date": 1726749113, "asset": null, "quantity": 4, "maker": "0xd4f4f6a1f386e041984da38e7be351903c767c2d", "taker": "", "payment": {"quantity": "1600000000000000", "token_address": "0x4200000000000000000000000000000000000006", "decimals": 18, "symbol": "WETH"}, "criteria": {"collection": {"slug": "boredape-baseclub"}, "contract": {"address": "0x0be0bb1097f4465b17b1ac3b22b5427d9cbf6d2c"}, "trait": null, "encoded_token_ids": null}, "event_timestamp": 1726747615, "is_private_listing": false}, {"event_type": "order", "order_hash": "0x52ee102be8b1b422ef106fb3df13e3dc396097269c81c78592b772d0ceaff5fa", "order_type": "collection_offer", "chain": "base", "protocol_address": "0x0000000000000068f116a894984e2db1123eb395", "start_date": 1726747610, "expiration_date": 1726749110, "asset": null, "quantity": 6, "maker": "0xd4f4f6a1f386e041984da38e7be351903c767c2d", "taker": "", "payment": {"quantity": "1200000000000000", "token_address": "0x4200000000000000000000000000000000000006", "decimals": 18, "symbol": "WETH"}, "criteria": {"collection": {"slug": "boredape-baseclub"}, "contract": {"address": "0x0be0bb1097f4465b17b1ac3b22b5427d9cbf6d2c"}, "trait": null, "encoded_token_ids": null}, "event_timestamp": 1726747612, "is_private_listing": false}, {"event_type": "order", "order_hash": "0xe2564acda14689baf1a6fd68ac5bcf931a7b5174da52881919aebe2b89b3e876", "order_type": "collection_offer", "chain": "base", "protocol_address": "0x0000000000000068f116a894984e2db1123eb395", "start_date": 1726746841, "expiration_date": 1726748341, "asset": null, "quantity": 2, "maker": "0xd4f4f6a1f386e041984da38e7be351903c767c2d", "taker": "", "payment": {"quantity": "1000000000000000", "token_address": "0x4200000000000000000000000000000000000006", "decimals": 18, "symbol": "WETH"}, "criteria": {"collection": {"slug": "boredape-baseclub"}, "contract": {"address": "0x0be0bb1097f4465b17b1ac3b22b5427d9cbf6d2c"}, "trait": null, "encoded_token_ids": null}, "event_timestamp": 1726746843, "is_private_listing": false}, {"event_type": "order", "order_hash": "0x4dc97b2eeb7b7d2599e5001c3c85671b4b663ca12d963ef33d26fd08ac3977bf", "order_type": "collection_offer", "chain": "base", "protocol_address": "0x0000000000000068f116a894984e2db1123eb395", "start_date": 1726746838, "expiration_date": 1726748338, "asset": null, "quantity": 4, "maker": "0xd4f4f6a1f386e041984da38e7be351903c767c2d", "taker": "", "payment": {"quantity": "1600000000000000", "token_address": "0x4200000000000000000000000000000000000006", "decimals": 18, "symbol": "WETH"}, "criteria": {"collection": {"slug": "boredape-baseclub"}, "contract": {"address": "0x0be0bb1097f4465b17b1ac3b22b5427d9cbf6d2c"}, "trait": null, "encoded_token_ids": null}, "event_timestamp": 1726746840, "is_private_listing": false}, {"event_type": "order", "order_hash": "0xd5acb64fed56dbcb1b9bca126e9ba03e1562fbc505cbdfd92c3207d8b57c2d6e", "order_type": "collection_offer", "chain": "base", "protocol_address": "0x0000000000000068f116a894984e2db1123eb395", "start_date": 1726746835, "expiration_date": 1726748335, "asset": null, "quantity": 6, "maker": "0xd4f4f6a1f386e041984da38e7be351903c767c2d", "taker": "", "payment": {"quantity": "1200000000000000", "token_address": "0x4200000000000000000000000000000000000006", "decimals": 18, "symbol": "WETH"}, "criteria": {"collection": {"slug": "boredape-baseclub"}, "contract": {"address": "0x0be0bb1097f4465b17b1ac3b22b5427d9cbf6d2c"}, "trait": null, "encoded_token_ids": null}, "event_timestamp": 1726746837, "is_private_listing": false}, {"event_type": "order", "order_hash": "0x5a60d1063fa58ef6484bcb22347267aa0ca6dcf7fbcc37063125ad7192c8a338", "order_type": "collection_offer", "chain": "base", "protocol_address": "0x0000000000000068f116a894984e2db1123eb395", "start_date": 1726746064, "expiration_date": 1726747564, "asset": null, "quantity": 2, "maker": "0xd4f4f6a1f386e041984da38e7be351903c767c2d", "taker": "", "payment": {"quantity": "1000000000000000", "token_address": "0x4200000000000000000000000000000000000006", "decimals": 18, "symbol": "WETH"}, "criteria": {"collection": {"slug": "boredape-baseclub"}, "contract": {"address": "0x0be0bb1097f4465b17b1ac3b22b5427d9cbf6d2c"}, "trait": null, "encoded_token_ids": null}, "event_timestamp": 1726746066, "is_private_listing": false}, {"event_type": "order", "order_hash": "0x11863259781c5d712be74e9c04b97b21a00b3d276c95134504dd7a02f6a1a218", "order_type": "collection_offer", "chain": "base", "protocol_address": "0x0000000000000068f116a894984e2db1123eb395", "start_date": 1726746061, "expiration_date": 1726747561, "asset": null, "quantity": 4, "maker": "0xd4f4f6a1f386e041984da38e7be351903c767c2d", "taker": "", "payment": {"quantity": "1600000000000000", "token_address": "0x4200000000000000000000000000000000000006", "decimals": 18, "symbol": "WETH"}, "criteria": {"collection": {"slug": "boredape-baseclub"}, "contract": {"address": "0x0be0bb1097f4465b17b1ac3b22b5427d9cbf6d2c"}, "trait": null, "encoded_token_ids": null}, "event_timestamp": 1726746063, "is_private_listing": false}, {"event_type": "order", "order_hash": "0x5f97e5a3ef43a12adac235fb1a28d7dfa703ea3e660c640ac8803c0e65325fb7", "order_type": "collection_offer", "chain": "base", "protocol_address": "0x0000000000000068f116a894984e2db1123eb395", "start_date": 1726746058, "expiration_date": 1726747557, "asset": null, "quantity": 6, "maker": "0xd4f4f6a1f386e041984da38e7be351903c767c2d", "taker": "", "payment": {"quantity": "1200000000000000", "token_address": "0x4200000000000000000000000000000000000006", "decimals": 18, "symbol": "WETH"}, "criteria": {"collection": {"slug": "boredape-baseclub"}, "contract": {"address": "0x0be0bb1097f4465b17b1ac3b22b5427d9cbf6d2c"}, "trait": null, "encoded_token_ids": null}, "event_timestamp": 1726746060, "is_private_listing": false}, {"event_type": "order", "order_hash": "0xec07f80647fa243e245972bffe92344ae3ec7cc06f4aa880e77522d19d0028ea", "order_type": "collection_offer", "chain": "base", "protocol_address": "0x0000000000000068f116a894984e2db1123eb395", "start_date": 1726745326, "expiration_date": 1726746826, "asset": null, "quantity": 2, "maker": "0xd4f4f6a1f386e041984da38e7be351903c767c2d", "taker": "", "payment": {"quantity": "1000000000000000", "token_address": "0x4200000000000000000000000000000000000006", "decimals": 18, "symbol": "WETH"}, "criteria": {"collection": {"slug": "boredape-baseclub"}, "contract": {"address": "0x0be0bb1097f4465b17b1ac3b22b5427d9cbf6d2c"}, "trait": null, "encoded_token_ids": null}, "event_timestamp": 1726745327, "is_private_listing": false}, {"event_type": "order", "order_hash": "0x9171514ae29eb6a78dabbc67441e12ecdd6402dd538c36a757c519157c6eef9a", "order_type": "collection_offer", "chain": "base", "protocol_address": "0x0000000000000068f116a894984e2db1123eb395", "start_date": 1726745323, "expiration_date": 1726746822, "asset": null, "quantity": 4, "maker": "0xd4f4f6a1f386e041984da38e7be351903c767c2d", "taker": "", "payment": {"quantity": "1600000000000000", "token_address": "0x4200000000000000000000000000000000000006", "decimals": 18, "symbol": "WETH"}, "criteria": {"collection": {"slug": "boredape-baseclub"}, "contract": {"address": "0x0be0bb1097f4465b17b1ac3b22b5427d9cbf6d2c"}, "trait": null, "encoded_token_ids": null}, "event_timestamp": 1726745324, "is_private_listing": false}, {"event_type": "order", "order_hash": "0x5e0f3b811ccd4aaa99b55337ee77deecc9d171e78f84f98cfdf1adb11668a709", "order_type": "collection_offer", "chain": "base", "protocol_address": "0x0000000000000068f116a894984e2db1123eb395", "start_date": 1726745319, "expiration_date": 1726746818, "asset": null, "quantity": 6, "maker": "0xd4f4f6a1f386e041984da38e7be351903c767c2d", "taker": "", "payment": {"quantity": "1200000000000000", "token_address": "0x4200000000000000000000000000000000000006", "decimals": 18, "symbol": "WETH"}, "criteria": {"collection": {"slug": "boredape-baseclub"}, "contract": {"address": "0x0be0bb1097f4465b17b1ac3b22b5427d9cbf6d2c"}, "trait": null, "encoded_token_ids": null}, "event_timestamp": 1726745321, "is_private_listing": false}, {"event_type": "order", "order_hash": "0xe0c9fcb6367f1df2670461d2a9b975bfbfbb111acb2897f309f1a66ac64de4c9", "order_type": "collection_offer", "chain": "base", "protocol_address": "0x0000000000000068f116a894984e2db1123eb395", "start_date": 1726744561, "expiration_date": 1726746061, "asset": null, "quantity": 2, "maker": "0xd4f4f6a1f386e041984da38e7be351903c767c2d", "taker": "", "payment": {"quantity": "1000000000000000", "token_address": "0x4200000000000000000000000000000000000006", "decimals": 18, "symbol": "WETH"}, "criteria": {"collection": {"slug": "boredape-baseclub"}, "contract": {"address": "0x0be0bb1097f4465b17b1ac3b22b5427d9cbf6d2c"}, "trait": null, "encoded_token_ids": null}, "event_timestamp": 1726744563, "is_private_listing": false}]